{"Id":62,"Name":"Color Spray","School":"illusion","Level":1,"PageContent":"Source: Player\u0027s Handbook\n1st-level illusion\nCasting Time: 1 action\nRange: Self (15-foot cone)\nComponents: V, S, M (a pinch of powder or sand that is colored red, yellow, and blue)\nDuration: 1 round\nA dazzling array of flashing, colored light springs from your hand. Roll 6d10, the total is how many hit points of creatures this spell can effect. Creatures in a 15-foot cone originating from you are affected in ascending order of their current hit points (ignoring unconscious creatures and creatures that can\u2019t see).\nStarting with the creature that has the lowest current hit points, each creature affected by this spell is blinded until the end of your next turn. Subtract each creature\u2019s hit points from the total before moving on to the creature with the next lowest hit points. A creature\u2019s hit points must be equal to or less than the remaining total for the creature to be affected.\nAt Higher Levels. When you cast this spell using a spell slot of 2nd level or higher, roll an additional 2d10 for each slot level above 1st.\nSpell Lists. Bard (Optional), Sorcerer, Wizard","InLists":["Bard (Optional)","Sorcerer","Wizard"],"Source":"Player\u0027s Handbook","CastingTime":"1 action","Components":["V","S","M (a pinch of powder or sand that is colored red","yellow","and blue)"],"Range":"self (15-foot cone)","Duration":"1 round","WikidotLink":"http://dnd5e.wikidot.com//spell:color-spray"}