{"Id":297,"Name":"Conjure Woodland Beings","School":"conjuration","Level":4,"PageContent":"Source: Player\u0027s Handbook\n4th-level conjuration\nCasting Time: 1 action\nRange: 60 feet\nComponents: V, S, M (one holly berry per creature summoned)\nDuration: Concentration, up to 1 hour\nYou summon fey creatures that appear in unoccupied spaces that you can see within range. Choose one of the following options for what appears:\nOne fey creature of challenge rating 2 or lower\nTwo fey creatures of challenge rating 1 or lower\nFour fey creatures of challenge rating 1/2 or lower\nEight fey creatures of challenge rating 1/4 or lower\nA summoned creature disappears when it drops to 0 hit points or when the spell ends.\nThe summoned creatures are friendly to you and your companions. Roll initiative for the summoned creatures as a group, which have their own turns. They obey any verbal commands that you issue to them (no action required by you). If you don\u2019t issue any commands to them, they defend themselves from hostile creatures, but otherwise take no actions. The DM has the creatures\u2019 statistics.\nAt Higher Levels. When you cast this spell using certain higher-level spell slots, you choose one of the summoning options above, and more creatures appear: twice as many with a 6th-level slot, and three times as many with an 8th-level slot.\nSpell Lists. Druid, Ranger","InLists":["Druid","Ranger"],"Source":"Player\u0027s Handbook","CastingTime":"1 action","Components":["V","S","M (one holly berry per creature summoned)"],"Range":"60 feet","Duration":"concentration, up to 1 hour","WikidotLink":"http://dnd5e.wikidot.com//spell:conjure-woodland-beings"}