{"Id":300,"Name":"Dimension Door","School":"conjuration","Level":4,"PageContent":"Source: Player\u0027s Handbook\n4th-level conjuration\nCasting Time: 1 action\nRange: 500 feet\nComponents: V\nDuration: Instantaneous\nYou teleport yourself from your current location to any other spot within range. You arrive at exactly the spot desired. It can be a place you can see, one you can visualize, or one you can describe by stating distance and direction, such as \u0026quot;200 feet straight downward\u0026quot; or \u0026quot;upward to the northwest at a 45-degree angle, 300 feet\u0026quot;.\nYou can bring along objects as long as their weight doesn\u2019t exceed what you can carry. You can also bring one willing creature of your size or smaller who is carrying gear up to its carrying capacity. The creature must be within 5 feet of you when you cast this spell.\nIf you would arrive in a place already occupied by an object or a creature, you and any creature traveling with you each take 4d6 force damage, and the spell fails to teleport you.\nSpell Lists. Bard, Sorcerer, Warlock, Wizard","InLists":["Bard","Sorcerer","Warlock","Wizard"],"Source":"Player\u0027s Handbook","CastingTime":"1 action","Components":["V"],"Range":"500 feet","Duration":"instantaneous","WikidotLink":"http://dnd5e.wikidot.com//spell:dimension-door"}