{"Id":459,"Name":"Divine Word","School":"evocation","Level":7,"PageContent":"Source: Player\u0027s Handbook\n7th-level evocation\nCasting Time: 1 bonus action\nRange: 30 feet\nComponents: V\nDuration: Instantaneous\nYou utter a divine word, imbued with the power that shaped the world at the dawn of creation. Choose any number of creatures you can see within range. Each creature that can hear you must make a Charisma saving throw. On a failed save, a creature suffers an effect based on its current hit points:\n50 hit points or fewer: deafened for 1 minute\n40 hit points or fewer: deafened and blinded for 10 minutes\n30 hit points or fewer: blinded, deafened, and stunned for 1 hour\n20 hit points or fewer: killed instantly\nRegardless of its current hit points, a celestial, an elemental, a fey, or a fiend that fails its save is forced back to its plane of origin (if it isn\u2019t there already) and can\u2019t return to your current plane for 24 hours by any means short of a wish spell.\nSpell Lists. Cleric","InLists":["Cleric"],"Source":"Player\u0027s Handbook","CastingTime":"1 bonus action","Components":["V"],"Range":"30 feet","Duration":"instantaneous","WikidotLink":"http://dnd5e.wikidot.com//spell:divine-word"}