{"Id":244,"Name":"Haste","School":"transmutation","Level":3,"PageContent":"Source: Player\u0027s Handbook\n3rd-level transmutation\nCasting Time: 1 action\nRange: 30 feet\nComponents: V, S, M (a shaving of licorice root)\nDuration: Concentration, up to 1 minute\nChoose a willing creature that you can see within range. Until the spell ends, the target\u2019s speed is doubled, it gains a \u002B2 bonus to AC, it has advantage on Dexterity saving throws, and it gains an additional action on each of its turns. That action can be used only to take the Attack (one weapon attack only), Dash, Disengage, Hide, or Use an Object action.\nWhen the spell ends, the target can\u2019t move or take actions until after its next turn, as a wave of lethargy sweeps over it.\nSpell Lists. Artificer, Sorcerer, Wizard","InLists":["Artificer","Sorcerer","Wizard"],"Source":"Player\u0027s Handbook","CastingTime":"1 action","Components":["V","S","M (a shaving of licorice root)"],"Range":"30 feet","Duration":"concentration, up to 1 minute","WikidotLink":"http://dnd5e.wikidot.com//spell:haste"}