{"Id":93,"Name":"Hex","School":"enchantment","Level":1,"PageContent":"Source: Player\u0027s Handbook\n1st-level enchantment\nCasting Time: 1 bonus action\nRange: 90 feet\nComponents: V, S, M (the petrified eye of a newt)\nDuration: Concentration, up to 1 hour\nYou place a curse on a creature that you can see within range. Until the spell ends, you deal an extra 1d6 necrotic damage to the target whenever you hit it with an attack. Also, choose one ability when you cast the spell. The target has disadvantage on ability checks made with the chosen ability.\nIf the target drops to 0 hit points before this spell ends, you can use a bonus action on a subsequent turn of yours to curse a new creature.\nA Remove Curse cast on the target ends this spell early.\nAt Higher Levels. When you cast this spell using a spell slot of 3rd or 4th level, you can maintain your concentration on the spell for up to 8 hours. When you use a spell slot of 5th level or higher, you can maintain your concentration on the spell for up to 24 hours.\nSpell Lists. Warlock","InLists":["Warlock"],"Source":"Player\u0027s Handbook","CastingTime":"1 bonus action","Components":["V","S","M (the petrified eye of a newt)"],"Range":"90 feet","Duration":"concentration, up to 1 hour","WikidotLink":"http://dnd5e.wikidot.com//spell:hex"}