{"Id":164,"Name":"Hold Person","School":"enchantment","Level":2,"PageContent":"Source: Player\u0027s Handbook\n2nd-level enchantment\nCasting Time: 1 action\nRange: 60 feet\nComponents: V, S, M (a small, straight piece of iron)\nDuration: Concentration, up to 1 minute\nChoose a humanoid that you can see within range. The target must succeed on a Wisdom saving throw or be paralyzed for the duration. At the end of each of its turns, the target can make another Wisdom saving throw. On a success, the spell ends on the target.\nAt Higher Levels. When you cast this spell using a spell slot of 3rd level or higher, you can target one additional humanoid for each slot level above 2nd. The humanoids must be within 30 feet of each other when you target them.\nSpell Lists. Bard, Cleric, Druid, Sorcerer, Warlock, Wizard","InLists":["Bard","Cleric","Druid","Sorcerer","Warlock","Wizard"],"Source":"Player\u0027s Handbook","CastingTime":"1 action","Components":["V","S","M (a small","straight piece of iron)"],"Range":"60 feet","Duration":"concentration, up to 1 minute","WikidotLink":"http://dnd5e.wikidot.com//spell:hold-person"}