{"Id":173,"Name":"Locate Object","School":"divination","Level":2,"PageContent":"Source: Player\u0027s Handbook\n2nd-level divination\nCasting Time: 1 action\nRange: Self\nComponents: V, S, M (a forked twig)\nDuration: Concentration, up to 10 minutes\nDescribe or name an object that is familiar to you. You sense the direction to the object\u2019s location, as long as that object is within 1,000 feet of you. If the object is in motion, you know the direction of its movement.\nThe spell can locate a specific object known to you, as long as you have seen it up close \u2013 within 30 feet \u2013 at least once. Alternatively, the spell can locate the nearest object of a particular kind, such as a certain kind of apparel, jewelry, furniture, tool, or weapon.\nThis spell can\u2019t locate an object if any thickness of lead, even a thin sheet, blocks a direct path between you and the object.\nSpell Lists. Bard, Cleric, Druid, Paladin, Ranger, Wizard","InLists":["Bard","Cleric","Druid","Paladin","Ranger","Wizard"],"Source":"Player\u0027s Handbook","CastingTime":"1 action","Components":["V","S","M (a forked twig)"],"Range":"self","Duration":"concentration, up to 10 minutes","WikidotLink":"http://dnd5e.wikidot.com//spell:locate-object"}