{"Id":498,"Name":"Maddening Darkness","School":"evocation","Level":8,"PageContent":"Source: Xanathar\u0027s Guide to Everything\n8th-level evocation\nCasting Time: 1 action\nRange: 150 feet\nComponents: V, M (a drop of pitch mixed with a drop of mercury)\nDuration: Concentration, up to 10 minutes\nMagical darkness spreads from a point you choose within range to fill a 60-foot-radius sphere until the spell ends. The darkness spreads around corners. A creature with darkvision can\u2019t see through this darkness. Nonmagical light, as well as light created by spells of 8th level or lower, can\u0027t illuminate the area. Shrieks, gibbering, and mad laughter can be heard within the sphere. Whenever a creature starts its turn in the sphere, it must make a Wisdom saving throw, taking 8d8 psychic damage on a failed save, or half as much damage on a successful one.\nSpell Lists. Warlock, Wizard","InLists":["Warlock","Wizard"],"Source":"Xanathar\u0027s Guide to Everything","CastingTime":"1 action","Components":["V","M (a drop of pitch mixed with a drop of mercury)"],"Range":"150 feet","Duration":"concentration, up to 10 minutes","WikidotLink":"http://dnd5e.wikidot.com//spell:maddening-darkness"}