{"Id":321,"Name":"Mordenkainen\u0027s Faithful Hound","School":"conjuration","Level":4,"PageContent":"Source: Player\u0027s Handbook\n4th-level conjuration\nCasting Time: 1 action\nRange: 30 feet\nComponents: V, S, M (a tiny silver whistle, a piece of bone, and a thread)\nDuration: 8 hours\nYou conjure a phantom watchdog in an unoccupied space that you can see within range, where it remains for the duration, until you dismiss it as an action, or until you move more than 100 feet away from it.\nThe hound is invisible to all creatures except you and can\u2019t be harmed. When a Small or larger creature comes within 30 feet of it without first speaking the password that you specify when you cast this spell, the hound starts barking loudly. The hound sees invisible creatures and can see into the Ethereal Plane. It ignores illusions.\nAt the start of each of your turns, the hound attempts to bite one creature within 5 feet of it that is hostile to you. The hound\u2019s attack bonus is equal to your spellcasting ability modifier \u002B your proficiency bonus. On a hit, it deals 4d8 piercing damage.\nSpell Lists. Artificer, Wizard","InLists":["Artificer","Wizard"],"Source":"Player\u0027s Handbook","CastingTime":"1 action","Components":["V","S","M (a tiny silver whistle","a piece of bone","and a thread)"],"Range":"30 feet","Duration":"8 hours","WikidotLink":"http://dnd5e.wikidot.com//spell:mordenkainens-faithful-hound"}