{"Id":182,"Name":"Nathair\u0027s Mischief","School":"illusion","Level":2,"PageContent":"Source: Fizban\u0027s Treasury of Dragons\n2nd-level Illusion\nCasting Time: 1 Action\nRange: 60ft\nComponents: S, M (a piece of crust from an apple pie)\nDuration: Concentration, up to 1 minute\nYou fill a 20-foot cube you can see within range with fey and draconic magic. Roll on the Mischievous Surge table to determine the magical effect produced, and roll again at the start of each of your turns until the spell ends. You can move the cube up to 10 feet before you roll.\nMischievous Surge\nd4\nEffect\n1\nThe smell of apple pie fills the air, and each creature in the cube must succeed on a Wisdom saving throw or become charmed by you until the start of your next turn.\n2\nBouquets of flowers appear all around, and each creature in the cube must succeed on a Dexterity saving throw or be blinded until the start of your next turn as the flowers spray water in their faces.\n3\nEach creature in the cube must succeed on a Wisdom saving throw or begin giggling until the start of your next turn. A giggling creature is incapacitated and uses all its movement to move in a random direction.\n4\nDrops of molasses appear and hover in the cube, turning it into difficult terrain until the start of your next turn.\nSpell Lists. Bard, Sorcerer, Wizard","InLists":["Bard","Sorcerer","Wizard"],"Source":"Fizban\u0027s Treasury of Dragons","CastingTime":"1 action","Components":["S","M (a piece of crust from an apple pie)"],"Range":"60ft","Duration":"concentration, up to 1 minute","WikidotLink":"http://dnd5e.wikidot.com//spell:nathairs-mischief"}