{"Id":28,"Name":"Prestidigitation","School":"transmutation","Level":0,"PageContent":"Source: Player\u0027s Handbook\nTransmutation cantrip\nCasting Time: 1 action\nRange: 10 feet\nComponents: V, S\nDuration: Up to 1 hour\nThis spell is a minor magical trick that novice spellcasters use for practice. You create one of the following magical effects within range:\nYou create an instantaneous, harmless sensory effect, such as a shower of sparks, a puff of wind, faint musical notes, or an odd odor.\nYou instantaneously light or snuff out a candle, a torch, or a small campfire.\nYou instantaneously clean or soil an object no larger than 1 cubic foot.\nYou chill, warm, or flavor up to 1 cubic foot of nonliving material for 1 hour.\nYou make a color, a small mark, or a symbol appear on an object or a surface for 1 hour.\nYou create a nonmagical trinket or an illusory image that can fit in your hand and that lasts until the end of your next turn.\nIf you cast this spell multiple times, you can have up to three of its non-instantaneous effects active at a time, and you can dismiss such an effect as an action.\nSpell Lists. Artificer, Bard, Sorcerer, Warlock, Wizard","InLists":["Artificer","Bard","Sorcerer","Warlock","Wizard"],"Source":"Player\u0027s Handbook","CastingTime":"1 action","Components":["V","S"],"Range":"10 feet","Duration":"up to 1 hour","WikidotLink":"http://dnd5e.wikidot.com//spell:prestidigitation"}