{"Id":105,"Name":"Protection from Evil and Good","School":"abjuration","Level":1,"PageContent":"Source: Player\u0027s Handbook\n1st-level abjuration\nCasting Time: 1 action\nRange: Touch\nComponents: V, S, M (holy water or powdered silver and iron, which the spell consumes)\nDuration: Concentration, up to 10 minutes\nUntil the spell ends, one willing creature you touch is protected against certain types of creatures: aberrations, celestials, elementals, fey, fiends, and undead.\nThe protection grants several benefits. Creatures of those types have disadvantage on attack rolls against the target. The target also can\u0027t be charmed, frightened, or possessed by them. If the target is already charmed, frightened, or possessed by such a creature, the target has advantage on any new saving throw against the relevant effect.\nSpell Lists. Cleric, Druid (Optional), Paladin, Warlock, Wizard","InLists":["Cleric","Druid (Optional)","Paladin","Warlock","Wizard"],"Source":"Player\u0027s Handbook","CastingTime":"1 action","Components":["V","S","M (holy water or powdered silver and iron","which the spell consumes)"],"Range":"touch","Duration":"concentration, up to 10 minutes","WikidotLink":"http://dnd5e.wikidot.com//spell:protection-from-evil-and-good"}