{"Id":519,"Name":"Psychic Scream","School":"enchantment","Level":9,"PageContent":"Source: Xanathar\u0027s Guide to Everything\n9th-level enchantment\nCasting Time: 1 action\nRange: 90 feet\nComponents: S\nDuration: Instantaneous\nYou unleash the power of your mind to blast the intellect of up to ten creatures of your choice that you can see within range. Creatures that have an Intelligence score of 2 or lower are unaffected.\nEach target must make an Intelligence saving throw. On a failed save, a target takes 14d6 psychic damage and is stunned. On a successful save, a target takes half as much damage and isn\u2019t stunned. If a target is killed by this damage, its head explodes, assuming it has one.\nA stunned target can make an Intelligence saving throw at the end of each of its turns. On a successful save, the stunning effect ends.\nSpell Lists. Bard, Sorcerer, Warlock, Wizard","InLists":["Bard","Sorcerer","Warlock","Wizard"],"Source":"Xanathar\u0027s Guide to Everything","CastingTime":"1 action","Components":["S"],"Range":"90 feet","Duration":"instantaneous","WikidotLink":"http://dnd5e.wikidot.com//spell:psychic-scream"}