{"Id":108,"Name":"Sanctuary","School":"abjuration","Level":1,"PageContent":"Source: Player\u0027s Handbook\n1st-level abjuration\nCasting Time: 1 bonus action\nRange: 30 feet\nComponents: V, S, M (a small silver mirror)\nDuration: 1 minute\nYou ward a creature within range against attack. Until the spell ends, any creature who targets the warded creature with an attack or a harmful spell must first make a Wisdom saving throw. On a failed save, the creature must choose a new target or lose the attack or spell. This spell doesn\u2019t protect the warded creature from area effects, such as the explosion of a fireball.\nIf the warded creature makes an attack, casts a spell that affects an enemy, or deals damage to another creature, this spell ends.\nSpell Lists. Artificer, Cleric","InLists":["Artificer","Cleric"],"Source":"Player\u0027s Handbook","CastingTime":"1 bonus action","Components":["V","S","M (a small silver mirror)"],"Range":"30 feet","Duration":"1 minute","WikidotLink":"http://dnd5e.wikidot.com//spell:sanctuary"}