{"Id":113,"Name":"Silvery Barbs","School":"enchantment","Level":1,"PageContent":"Source: Strixhaven: A Curriculum of Chaos\n1st-level Enchantment\nCasting Time: 1 reaction, which you take when a creature you can see within 60 feet of yourself succeeds on an attack roll, an ability check, or a saving throw\nRange: 60 feet\nComponents: V\nDuration: Instantaneous\nYou magically distract the triggering creature and turn its momentary uncertainty into encouragement for another creature. The triggering creature must reroll the d20 and use the lower roll.\nYou can then choose a different creature you can see within range (you can choose yourself). The chosen creature has advantage on the next attack roll, ability check, or saving throw it makes within 1 minute. A creature can be empowered by only one use of this spell at a time.\nSpell Lists. Bard, Sorcerer, Wizard","InLists":["Bard","Sorcerer","Wizard"],"Source":"Strixhaven","CastingTime":"1 reaction, which you take when a creature you can see within 60 feet of yourself succeeds on an attack roll, an ability check, or a saving throw","Components":["V"],"Range":"60 feet","Duration":"instantaneous","WikidotLink":"http://dnd5e.wikidot.com//spell:silvery-barbs"}