{"Id":267,"Name":"Sleet Storm","School":"conjuration","Level":3,"PageContent":"Source: Player\u0027s Handbook\n3rd-level conjuration\nCasting Time: 1 action\nRange: 120 feet\nComponents: V, S, M (a pinch of dust and a few drops of water)\nDuration: Concentration, up to 1 minute\nUntil the spell ends, freezing rain and sleet fall in a 20-foot-tall cylinder with a 40-foot radius centered on a point you choose within range. The area is heavily obscured, and exposed flames in the area are doused.\nThe ground in the area is covered with slick ice, making it difficult terrain. When a creature enters the spell\u2019s area for the first time on a turn or starts its turn there, it must make a Dexterity saving throw. On a failed save, it falls prone.\nIf a creature starts its turn in the spell\u0027s area and is concentrating on a spell, the creature must make a successful Constitution saving throw against your spell save DC or lose concentration.\nSpell Lists. Druid, Sorcerer, Wizard","InLists":["Druid","Sorcerer","Wizard"],"Source":"Player\u0027s Handbook","CastingTime":"1 action","Components":["V","S","M (a pinch of dust and a few drops of water)"],"Range":"120 feet","Duration":"concentration, up to 1 minute","WikidotLink":"http://dnd5e.wikidot.com//spell:sleet-storm"}