{"Id":445,"Name":"Sunbeam","School":"evocation","Level":6,"PageContent":"Source: Player\u0027s Handbook\n6th-level evocation\nCasting Time: 1 action\nRange: Self (60-foot line)\nComponents: V, S, M (a magnifying glass)\nDuration: Concentration, up to 1 minute\nA beam of brilliant light flashes out from your hand in a 5-foot-wide, 60-foot-line. Each creature in the line must make a Constitution saving throw. On a failed save, a creature takes 6d8 radiant damage and is blinded until your next turn. On a successful save, it takes half as much damage and isn\u2019t blinded by this spell. Undead and oozes have disadvantage on this saving throw.\nYou can create a new line of radiance as your action on any turn until the spell ends.\nFor the duration, a mote of brilliant radiance shines in your hand. It sheds bright light in a 30-foot radius and dim light for an additional 30 feet. The light is sunlight.\nSpell Lists. Cleric (Optional), Druid, Sorcerer, Wizard","InLists":["Cleric (Optional)","Druid","Sorcerer","Wizard"],"Source":"Player\u0027s Handbook","CastingTime":"1 action","Components":["V","S","M (a magnifying glass)"],"Range":"self (60-foot line)","Duration":"concentration, up to 1 minute","WikidotLink":"http://dnd5e.wikidot.com//spell:sunbeam"}