{"Id":447,"Name":"Tenser\u0027s Transformation","School":"transmutation","Level":6,"PageContent":"Source: Xanathar\u0027s Guide to Everything\n6th-level transmutation\nCasting Time: 1 action\nRange: Self\nComponents: V, S, M (a few hairs from a bull)\nDuration: Concentration, up to 10 minutes\nYou endow yourself with endurance and martial prowess fueled by magic. Until the spell ends, you can\u2019t cast spells, and you gain the following benefits:\nYou gain 50 temporary hit points. If any of these remain when the spell ends, they are lost.\nYou have advantage on attack rolls that you make with simple and martial weapons.\nWhen you hit a target with a weapon attack, that target takes an extra 2d12 force damage.\nYou have proficiency with all armor, shields, simple weapons, and martial weapons.\nYou have proficiency in Strength and Constitution saving throws.\nYou can attack twice, instead of once, when you take the Attack action on your turn. You ignore this benefit if you already have a feature, like Extra Attack, that gives you extra attacks.\nImmediately after the spell ends, you must succeed on a DC 15 Constitution saving throw or suffer one level of exhaustion.\nSpell Lists. Wizard","InLists":["Wizard"],"Source":"Xanathar\u0027s Guide to Everything","CastingTime":"1 action","Components":["V","S","M (a few hairs from a bull)"],"Range":"self","Duration":"concentration, up to 10 minutes","WikidotLink":"http://dnd5e.wikidot.com//spell:tensers-transformation"}