{"Id":279,"Name":"Tidal Wave","School":"conjuration","Level":3,"PageContent":"Source: Xanathar\u0027s Guide to Everything\n3rd-level conjuration\nCasting Time: 1 action\nRange: 120 feet\nComponents: V, S, M (a drop of water)\nDuration: Instantaneous\nYou conjure up a wave of water that crashes down on an area within range. The area can be up to 30 feet long, up to 10 feet wide, and up to 10 feet tall. Each creature in that area must make a Dexterity saving throw. On a failure, a creature takes 4d8 bludgeoning damage and is knocked prone. On a success, a creature takes half as much damage and isn\u2019t knocked prone. The water then spreads out across the ground in all directions, extinguishing unprotected flames in its area and within 30 feet of it.\nSpell Lists. Druid, Sorcerer, Wizard","InLists":["Druid","Sorcerer","Wizard"],"Source":"Xanathar\u0027s Guide to Everything","CastingTime":"1 action","Components":["V","S","M (a drop of water)"],"Range":"120 feet","Duration":"instantaneous","WikidotLink":"http://dnd5e.wikidot.com//spell:tidal-wave"}