{"Id":208,"Name":"Warding Wind","School":"evocation","Level":2,"PageContent":"Source: Xanathar\u0027s Guide to Everything\n2nd-level evocation\nCasting Time: 1 action\nRange: Self\nComponents: V\nDuration: Concentration, up to 10 minutes\nA strong wind (20 miles per hour) blows around you in a 10-foot radius and moves with you, remaining centered on you. The wind lasts for the spell\u2019s duration.\nThe wind has the following effects:\nIt deafens you and other creatures in its area.\nIt extinguishes unprotected flames in its area that are torch-sized or smaller.\nThe area is difficult terrain for creatures other than you.\nThe attack rolls of ranged weapon attacks have disadvantage if they pass in or out of the wind.\nIt hedges out vapor, gas, and fog that can be dispersed by strong wind.\nSpell Lists. Bard, Druid, Sorcerer, Wizard","InLists":["Bard","Druid","Sorcerer","Wizard"],"Source":"Xanathar\u0027s Guide to Everything","CastingTime":"1 action","Components":["V"],"Range":"self","Duration":"concentration, up to 10 minutes","WikidotLink":"http://dnd5e.wikidot.com//spell:warding-wind"}