{"Id":209,"Name":"Warp Sense","School":"divination","Level":2,"PageContent":"Source: Planescape - Adventures in the Multiverse\n2nd-Level divination\nCasting Time: 1 action\nRange: Self\nComponents: V, S, M (a razorvine leaf)\nDuration: Concentration, up to 1 minute\nFor the duration, you sense the presence of portals, even inactive ones, within 30 feet of yourself.\nIf you detect a portal in this way, you can use your action to study it. Make a DC 15 ability check using your spellcasting ability. On a successful check, you learn the destination plane of the portal and what portal key it requires, then the spell ends. On a failed check, you learn nothing and can\u0027t study that portal again using this spell until you cast it again.\nThe spell can penetrate most barriers but is blocked by 1 foot of stone, 1 inch of common metal, a thin sheet of lead, or 3 feet of wood or dirt.\nSpell Lists. Sorcerer, Warlock, Wizard","InLists":["Sorcerer","Warlock","Wizard"],"Source":"Planescape - Adventures in the Multiverse","CastingTime":"1 action","Components":["V","S","M (a razorvine leaf)"],"Range":"self","Duration":"concentration, up to 1 minute","WikidotLink":"http://dnd5e.wikidot.com//spell:warp-sense"}