{"Name": "Air Bubble", "School": "conjuration", "Level": 2, "PageContent": "Source: Spelljammer: Adventures in Space - Astral Adventurer's Guide\n2nd-Level Conjuration\nCasting Time: 1 action\nRange: 60 feet\nComponents: S\nDuration: 24 hours\nYou create a spectral globe around the head of a willing creature you can see within range. The globe is filled with fresh air that lasts until the spell ends. If the creature has more than one head, the globe of air appears around only one of its heads (which is all the creature needs to avoid suffocation, assuming that all its heads share the same respiratory system).\nAt Higher Levels. When you cast this spell using a spell slot of 3rd level or higher, you can create two additional globes of fresh air for each slot level above 2nd.\nSpell Lists. Artificer, Druid, Ranger, Sorcerer, Wizard", "InLists": ["Artificer", "Druid", "Ranger", "Sorcerer", "Wizard"], "Source": "Spelljammer", "CastingTime": "1 action", "Components": ["S"], "Range": "60 feet", "Duration": "24 hours", "Id": 5}