{"Name":"Alarm","School":"abjuration","Level":1,"PageContent":"Source: Player\u0027s Handbook\n1st-level abjuration (ritual)\nCasting Time: 1 action\nRange: 30 feet\nComponents: V, S, M (a tiny bell and a piece of fine silver wire)\nDuration: 8 hours\nYou set an alarm against unwanted intrusion. Choose a door, a window, or an area within range that is no larger than a 20-foot cube. Until the spell ends, an alarm alerts you whenever a tiny or larger creature touches or enters the warded area. When you cast the spell, you can designate creatures that won\u2019t set off the alarm. You also choose whether the alarm is mental or audible.\nA mental alarm alerts you with a ping in your mind if you are within 1 mile of the warded area. This ping awakens you if you are sleeping. An audible alarm produces the sound of a hand bell for 10 seconds within 60 feet.\nSpell Lists. Artificer, Ranger, Wizard","InLists":["Artificer","Ranger","Wizard"],"Source":"Player\u0027s Handbook","CastingTime":"1 action","Components":["V","S","M (a tiny bell and a piece of fine silver wire)"],"Range":"30 feet","Duration":"8 hours"}