{"Id":286,"Name":"Arcane Eye","School":"divination","Level":4,"PageContent":"Source: Player\u0027s Handbook\n4th-level divination\nCasting Time: 1 action\nRange: 30 feet\nComponents: V, S, M (a bit of bat fur)\nDuration: Concentration, up to 1 hour\nYou create an invisible, magical eye within range that hovers in the air for the duration. You mentally receive visual information from the eye, which has normal vision and darkvision out to 30 feet. The eye can look in every direction.\nAs an action, you can move the eye up to 30 feet in any direction. There is no limit to how far away from you the eye can move, but it can\u2019t enter another plane of existence. A solid barrier blocks the eye\u2019s movement, but the eye can pass through an opening as small as 1 inch in diameter.\nSpell Lists. Artificer, Wizard","InLists":["Artificer","Wizard"],"Source":"Player\u0027s Handbook","CastingTime":"1 action","Components":["V","S","M (a bit of bat fur)"],"Range":"30 feet","Duration":"concentration, up to 1 hour"}