{"Name": "Arcane Lock", "School": "abjuration", "Level": 2, "PageContent": "Source: Player's Handbook\n2nd-level abjuration\nCasting Time: 1 action\nRange: Touch\nComponents: V, S, M (gold dust worth at least 25 gp, which the spell consumes)\nDuration: Until dispelled\nYou touch a closed door, window, gate, chest, or other entryway, and it becomes locked for the duration.\nYou and the creatures you designate when you cast this spell can open the object normally. You can also set a password that, when spoken within 5 feet of the object, suppresses this spell for 1 minute. Otherwise, it is impassable until it is broken or the spell is dispelled or suppressed. Casting knock on the object suppresses arcane lock for 10 minutes.\nWhile affected by this spell, the object is more difficult to break or force open; the DC to break it or pick any locks on it increases by 10.\nSpell Lists. Artificer, Wizard", "InLists": ["Artificer", "Wizard"], "Source": "Player's Handbook", "CastingTime": "1 action", "Components": ["V", "S", "M (gold dust worth at least 25 gp", "which the spell consumes)"], "Range": "touch", "Duration": "until dispelled", "Id": 18}