{"Id":215,"Name":"Ashardalon\u0027s Stride","School":"transmutation","Level":3,"PageContent":"Source: Fizban\u0027s Treasury of Dragons\n3rd-level Transmutation\nCasting Time: 1 bonus action\nRange: Self\nComponents: V,S\nDuration: Concentration, up to 1 minute\nThe billowing flames of a dragon blast from your feet, granting you explosive speed. For the duration, your speed increases by 20 feet and moving doesn\u2019t provoke opportunity attacks.\nWhen you move within 5 feet of a creature or an object that isn\u2019t being worn or carried, it takes 1d6 fire damage from your trail of heat. A creature or object can take this damage only once during a turn.\nAt Higher Levels. When you cast this spell using a spell slot of 4th level or higher, increase your speed by 5 feet for each spell slot level above 3rd. The spell deals an additional 1d6 fire damage for each slot level above 3rd.\nSpell Lists. Artificer, Ranger, Sorcerer, Wizard","InLists":["Artificer","Ranger","Sorcerer","Wizard"],"Source":"Fizban\u0027s Treasury of Dragons","CastingTime":"1 bonus action","Components":["V,S"],"Range":"self","Duration":"concentration, up to 1 minute","WikidotLink":"http://dnd5e.wikidot.com//spell:ashardalons-stride"}