{"Id":132,"Name":"Augury","School":"divination","Level":2,"PageContent":"Source: Player\u0027s Handbook\n2nd-level divination (ritual)\nCasting Time: 1 minute\nRange: Self\nComponents: V, S, M (specially marked sticks, bones, or similar tokens worth at least 25 gp)\nDuration: Instantaneous\nBy casting gem-inlaid sticks, rolling dragon bones, laying out ornate cards, or employing some other divining tool, you receive an omen from an otherworldly entity about the results of a specific course of action that you plan to take within the next 30 minutes. The DM chooses from the following possible omens:\nWeal, for good results\nWoe, for bad results\nWeal and woe, for both good and bad results\nNothing, for results that aren\u2019t especially good or bad\nThe spell doesn\u2019t take into account any possible circumstances that might change the outcome, such as the casting of additional spells or the loss or gain of a companion. If you cast the spell two or more times before completing your next long rest, there is a cumulative 25 percent chance for each casting after the first that you get a random reading. The DM makes this roll in secret.\nSpell Lists. Cleric, Druid (Optional), Wizard (Optional)","InLists":["Cleric","Druid (Optional)","Wizard (Optional)"],"Source":"Player\u0027s Handbook","CastingTime":"1 minute","Components":["V","S","M (specially marked sticks","bones","or similar tokens worth at least 25 gp)"],"Range":"self","Duration":"instantaneous","WikidotLink":"http://dnd5e.wikidot.com//spell:augury"}