{"Id":345,"Name":"Awaken","School":"transmutation","Level":5,"PageContent":"Source: Player\u0027s Handbook\n5th-level transmutation\nCasting Time: 8 hours\nRange: Touch\nComponents: V, S, M (an agate worth at least 1,000 gp, which the spell consumes)\nDuration: Instantaneous\nAfter spending the casting time tracing magical pathways within a precious gemstone, you touch a huge or smaller beast or plant. The target must have either no Intelligence score or an Intelligence of 3 or less.\nThe target gains an Intelligence of 10. The target also gains the ability to speak one language you know. If the target is a plant, it gains the ability to move its limbs, roots, vines, creepers, and so forth, and it gains senses similar to a human\u2019s. Your DM chooses statistics appropriate for the awakened plant, such as the statistics for the awakened shrub or the awakened tree.\nThe awakened beast or plant is charmed by you for 30 days or until you and your companions do anything harmful to it. When the charmed condition ends, the awakened creature chooses whether to remain friendly to you, based on how you treated it while it was charmed.\nSpell Lists. Bard, Druid","InLists":["Bard","Druid"],"Source":"Player\u0027s Handbook","CastingTime":"8 hours","Components":["V","S","M (an agate worth at least 1,000 gp","which the spell consumes)"],"Range":"touch","Duration":"instantaneous","WikidotLink":"http://dnd5e.wikidot.com//spell:awaken"}