{"Name": "Beast Bond", "School": "divination", "Level": 1, "PageContent": "Source: Xanathar's Guide to Everything\n1st-level divination\nCasting Time: 1 action\nRange: Touch\nComponents: V, S, M (a bit of fur wrapped in cloth)\nDuration: Concentration, up to 10 minutes\nYou establish a telepathic link with one beast you touch that is friendly to you or charmed by you. The spell fails if the beast\u2019s Intelligence is 4 or higher. Until the spell ends, the link is active while you and the beast are within line of sight of each other. Through the link, the beast can understand your telepathic messages to it, and it can telepathically communicate simple emotions and concepts back to you. While the link is active, the beast gains advantage on attack rolls against any creature within 5 feet of you that you can see.\nSpell Lists. Druid, Ranger", "InLists": ["Druid", "Ranger"], "Source": "Xanathar's Guide to Everything", "CastingTime": "1 action", "Components": ["V", "S", "M (a bit of fur wrapped in cloth)"], "Range": "touch", "Duration": "concentration, up to 10 minutes", "Id": 33}