{"Id":508,"Name":"Blade of Disaster","School":"conjuration","Level":9,"PageContent":"Source: Tasha\u0027s Cauldron of Everything\n9th-level conjuration\nCasting Time: 1 bonus action\nRange: 60 feet\nComponents: V, S\nDuration: Concentration, up to 1 minute\nYou create a blade-shaped planar rift about 3 feet long in an unoccupied space you can see within range. The blade lasts for the duration. When you cast this spell, you can make up to two melee spell attacks with the blade, each one against a creature, loose object, or structure within 5 feet of the blade. On a hit, the target takes 4d12 force damage. This attack scores a critical hit if the number on the d20 is 18 or higher. On a critical hit, the blade deals an extra 8d12 force damage (for a total of 12d12 force damage).\nAs a bonus action on your turn, you can move the blade up to 30 feet to an unoccupied space you can see and then make up to two melee spell attacks with it again.\nThe blade can harmlessly pass through any barrier, including a Wall of Force.\nSpell Lists. Sorcerer (Optional), Warlock (Optional), Wizard (Optional)","InLists":["Sorcerer (Optional)","Warlock (Optional)","Wizard (Optional)"],"Source":"Tasha\u0027s Cauldron of Everything","CastingTime":"1 bonus action","Components":["V","S"],"Range":"60 feet","Duration":"concentration, up to 1 minute","WikidotLink":"http://dnd5e.wikidot.com//spell:blade-of-disaster"}