{"Id":55,"Name":"Burning Hands","School":"evocation","Level":1,"PageContent":"Source: Player\u0027s Handbook\n1st-level evocation\nCasting Time: 1 action\nRange: Self (15-foot cone)\nComponents: V, S\nDuration: Instantaneous\nAs you hold your hands with thumbs touching and fingers spread, a thin sheet of flames shoots forth from your outstretched fingertips. Each creature in a 15-foot cone must make a Dexterity saving throw. A creature takes 3d6 fire damage on a failed save, or half as much damage on a successful one.\nThe fire ignites any flammable objects in the area that aren\u2019t being worn or carried.\nAt Higher Levels. When you cast this spell using a spell slot of 2nd level or higher, the damage increases by 1d6 for each slot level above 1st.\nSpell Lists. Sorcerer, Wizard","InLists":["Sorcerer","Wizard"],"Source":"Player\u0027s Handbook","CastingTime":"1 action","Components":["V","S"],"Range":"self (15-foot cone)","Duration":"instantaneous","WikidotLink":"http://dnd5e.wikidot.com//spell:burning-hands"}