{"Name": "Catapult", "School": "transmutation", "Level": 1, "PageContent": "Source: Xanathar's Guide to Everything\n1st-level transmutation\nCasting Time: 1 action\nRange: 60 feet\nComponents: S\nDuration: Instantaneous\nChoose one object weighing 1 to 5 pounds within range that isn\u2019t being worn or carried. The object flies in a straight line up to 90 feet in a direction you choose before falling to the ground, stopping early if it impacts against a solid surface. If the object would strike a creature, that creature must make a Dexterity saving throw. On a failed save, the object strikes the target and stops moving. When the object strikes something, the object and what it strikes each take 3d8 bludgeoning damage.\nAt Higher Levels. When you cast this spell using a spell slot of 2nd level or higher, the maximum weight of objects that you can target with this spell increases by 5 pounds, and the damage increases by 1d8, for each slot level above 1st.\nSpell Lists. Sorcerer, Wizard, Artificer", "InLists": ["Sorcerer", "Wizard", "Artificer"], "Source": "Xanathar's Guide to Everything", "CastingTime": "1 action", "Components": ["S"], "Range": "60 feet", "Duration": "instantaneous", "Id": 53}