{"Name": "Cause Fear", "School": "necromancy", "Level": 1, "PageContent": "Source: Xanathar's Guide to Everything\n1st-level necromancy\nCasting Time: 1 action\nRange: 60 feet\nComponents: V\nDuration: Concentration, up to 1 minute\nYou awaken the sense of mortality in one creature you can see within range. A construct or an undead is immune to this effect. The target must succeed on a Wisdom saving throw or become frightened of you until the spell ends. The frightened target can repeat the saving throw at the end of each of its turns, ending the effect on itself on a success.\nAt Higher Levels. When you cast this spell using a spell slot of 2nd level or higher, you can target one additional creature for each slot level above 1st. The creatures must be within 30 feet of each other when you target them.\nSpell Lists. Warlock, Wizard", "InLists": ["Warlock", "Wizard"], "Source": "Xanathar's Guide to Everything", "CastingTime": "1 action", "Components": ["V"], "Range": "60 feet", "Duration": "concentration, up to 1 minute", "Id": 55}