{"Name": "Chill Touch", "School": "necromancy", "Level": 0, "PageContent": "Source: Player's Handbook\nNecromancy cantrip\nCasting Time: 1 action\nRange: 120 feet\nComponents: V, S\nDuration: 1 round\nYou create a ghostly, skeletal hand in the space of a creature within range. Make a ranged spell attack against the creature to assail it with the chill of the grave. On a hit, the target takes 1d8 necrotic damage, and it can\u2019t regain hit points until the start of your next turn. Until then, the hand clings to the target. If you hit an undead target, it also has disadvantage on attack rolls against you until the end of your next turn.\nAt Higher Levels. This spell\u2019s damage increases by 1d8 when you reach 5th level (2d8), 11th level (3d8), and 17th level (4d8).\nSpell Lists. Sorcerer, Warlock, Wizard", "InLists": ["Sorcerer", "Warlock", "Wizard"], "Source": "Player's Handbook", "CastingTime": "1 action", "Components": ["V", "S"], "Range": "120 feet", "Duration": "1 round", "Id": 61}