{"Id":351,"Name":"Commune with Nature","School":"divination","Level":5,"PageContent":"Source: Player\u0027s Handbook\n5th-level divination (ritual)\nCasting Time: 1 minute\nRange: Self\nComponents: V, S\nDuration: Instantaneous\nYou briefly become one with nature and gain knowledge of the surrounding territory. In the outdoors, the spell gives you knowledge of the land within 3 miles of you. In caves and other natural underground settings, the radius is limited to 300 feet. The spell doesn\u2019t function where nature has been replaced by construction, such as in dungeons and towns.\nYou instantly gain knowledge of up to three facts of your choice about any of the following subjects as they relate to the area:\nterrain and bodies of water\nprevalent plants, minerals, animals, or peoples\npowerful celestials, fey, fiends, elementals, or undead\ninfluence from other planes of existence\nbuildings\nFor example, you could determine the location of powerful undead in the area, the location of major sources of safe drinking water, and the location of any nearby towns.\nSpell Lists. Druid, Ranger","InLists":["Druid","Ranger"],"Source":"Player\u0027s Handbook","CastingTime":"1 minute","Components":["V","S"],"Range":"self","Duration":"instantaneous","WikidotLink":"http://dnd5e.wikidot.com//spell:commune-with-nature"}