{"Name":"Compelled Duel","School":"enchantment","Level":1,"PageContent":"Source: Player\u0027s Handbook\n1st-level enchantment\nCasting Time: 1 bonus action\nRange: 30 feet\nComponents: V\nDuration: Concentration, up to 1 minute\nYou attempt to compel a creature into a duel. One creature that you can see within range must make a Wisdom saving throw. On a failed save, the creature is drawn to you, compelled by your divine demand. For the duration, it has disadvantage on attack rolls against creatures other than you, and must make a Wisdom saving throw each time it attempts to move to a space that is more than 30 feet away from you; if it succeeds on this saving throw, this spell doesn\u2019t restrict the target\u2019s movement for that turn.\nThe spell ends if you attack any other creature, if you cast a spell that targets a hostile creature other than the target, if a creature friendly to you damages the target or casts a harmful spell on it, or if you end your turn more than 30 feet away from the target.\nSpell Lists. Paladin","InLists":["Paladin"],"Source":"Player\u0027s Handbook","CastingTime":"1 bonus action","Components":["V"],"Range":"30 feet","Duration":"concentration, up to 1 minute"}