{"Name": "Contagion", "School": "necromancy", "Level": 5, "PageContent": "Source: Player's Handbook\n5th-level necromancy\nCasting Time: 1 action\nRange: Touch\nComponents: V, S\nDuration: 7 days\nYour touch inflicts disease. Make a melee spell attack against a creature within your reach. On a hit, the target is poisoned.\nAt the end of each of the poisoned target\u2019s turns, the target must make a Constitution saving throw. If the target succeeds on three of these saves, it is no longer poisoned, and the spell ends. If the target fails three of these saves, the target is no longer poisoned, but choose one of the diseases below. The target is subjected to the chosen disease for the spell\u2019s duration.\nSince this spell induces a natural disease in its target, any effect that removes a disease or otherwise ameliorates a disease\u2019s effects apply to it.\n\nBlinding Sickness. Pain grips the creature\u2019s mind, and its eyes turn milky white. The creature has disadvantage on Wisdom checks and Wisdom saving throws and is blinded.\n\n\nFilth Fever. A raging fever sweeps through the creature\u2019s body. The creature has disadvantage on Strength checks, Strength saving throws, and attack rolls that use Strength.\n\n\nFlesh Rot. The creature\u2019s flesh decays. The creature has disadvantage on Charisma checks and vulnerability to all damage.\n\n\nMindfire. The creature\u2019s mind becomes feverish. The creature has disadvantage on Intelligence checks and Intelligence saving throws, and the creature behaves as if under the effects of the confusion spell during combat.\n\n\nSeizure. The creature is overcome with shaking. The creature has disadvantage on Dexterity checks, Dexterity saving throws, and attack rolls that use Dexterity.\n\n\nSlimy Doom. The creature begins to bleed uncontrollably. The creature has disadvantage on Constitution checks and Constitution saving throws. In addition, whenever the creature takes damage, it is stunned until the end of its next turn.\n\nSpell Lists. Cleric, Druid", "InLists": ["Cleric", "Druid"], "Source": "Player's Handbook", "CastingTime": "1 action", "Components": ["V", "S"], "Range": "touch", "Duration": "7 days", "Id": 87}