{"Name": "Control Flames", "School": "transmutation", "Level": 0, "PageContent": "Source: Xanathar's Guide to Everything\nTransmutation cantrip\nCasting Time: 1 action\nRange: 60 feet\nComponents: S\nDuration: Instantaneous or 1 hour\nYou choose nonmagical flame that you can see within range and that fits within a 5-foot cube. You affect it in one of the following ways:\n\nYou instantaneously expand the flame 5 feet in one direction, provided that wood or other fuel is present in the new location.\n\n\nYou instantaneously extinguish the flames within the cube.\n\n\nYou double or halve the area of bright light and dim light cast by the flame, change its color, or both. The change lasts for 1 hour.\n\n\nYou cause simple shapes\u2014such as the vague form of a creature, an inanimate object, or a location\u2014to appear within the flames and animate as you like. The shapes last for 1 hour.\n\nIf you cast this spell multiple times, you can have up to three of its non-instantaneous effects active at a time, and you can dismiss such an effect as an action.\nSpell Lists. Druid, Sorcerer, Wizard", "InLists": ["Druid", "Sorcerer", "Wizard"], "Source": "Xanathar's Guide to Everything", "CastingTime": "1 action", "Components": ["S"], "Range": "60 feet", "Duration": "instantaneous or 1 hour", "Id": 90}