{"Id":484,"Name":"Control Weather","School":"transmutation","Level":8,"PageContent":"Source: Player\u0027s Handbook\n8th-level transmutation\nCasting Time: 10 minutes\nRange: Self (5-mile radius)\nComponents: V, S, M (burning incense and bits of earth and wood mixed in water)\nDuration: Concentration, Up to 8 hours\nYou take control of the weather within 5 miles of you for the duration. You must be outdoors to cast this spell. Moving to a place where you don\u2019t have a clear path to the sky ends the spell early.\nWhen you cast the spell, you change the current weather conditions, which are determined by the DM based on the climate and season. You can change precipitation, temperature, and wind. It takes 1d4 x 10 minutes for the new conditions to take effect. Once they do so, you can change the conditions again. When the spell ends, the weather gradually returns to normal.\nWhen you change the weather conditions, find a current condition on the following tables and change its stage by one, up or down. When changing the wind, you can change its direction.\n\n\nPrecipitation\n\n\nStage 1\nClear\n\n\nStage 2\nLight clouds\n\n\nStage 3\nOvercast or ground fog\n\n\nStage 4\nRain, hail or snow\n\n\nStage 5\nTorrential rain, driving hail or blizzard\n\n\n\n\nTemperature\n\n\nStage 1\nUnbearable heat\n\n\nStage 2\nHot\n\n\nStage 3\nWarm\n\n\nStage 4\nCool\n\n\nStage 5\nCold\n\n\nStage 6\nArctic cold\n\n\n\n\nWind\n\n\nStage 1\nCalm\n\n\nStage 2\nModerate wind\n\n\nStage 3\nStrong wind\n\n\nStage 4\nGale\n\n\nStage 5\nStorm\n\n\nSpell Lists. Cleric, Druid, Wizard","InLists":["Cleric","Druid","Wizard"],"Source":"Player\u0027s Handbook","CastingTime":"10 minutes","Components":["V","S","M (burning incense and bits of earth and wood mixed in water)"],"Range":"self (5-mile radius)","Duration":"concentration, up to 8 hours"}