{"Id":142,"Name":"Cordon of Arrows","School":"transmutation","Level":2,"PageContent":"Source: Player\u0027s Handbook\n2nd-level transmutation\nCasting Time: 1 action\nRange: 5 feet\nComponents: V, S, M (four or more arrows or bolts)\nDuration: 8 hours\nYou plant four pieces of nonmagical ammunition \u2013 arrows or crossbow bolts \u2013 in the ground within range and lay magic upon them to protect an area. Until the spell ends, whenever a creature other than you comes within 30 feet of the ammunition for the first time on a turn or ends its turn there, one piece of ammunition flies up to strike it. The creature must succeed on a Dexterity saving throw or take 1d6 piercing damage. The piece of ammunition is then destroyed. The spell ends when no ammunition remains.\nWhen you cast this spell, you can designate any creatures you choose, and the spell ignores them.\nAt Higher Levels. When you cast this spell using a spell slot of 3rd level or higher, the amount of ammunition that can be affected increases by two for each slot level above 2nd.\nSpell Lists. Ranger","InLists":["Ranger"],"Source":"Player\u0027s Handbook","CastingTime":"1 action","Components":["V","S","M (four or more arrows or bolts)"],"Range":"5 feet","Duration":"8 hours","WikidotLink":"http://dnd5e.wikidot.com//spell:cordon-of-arrows"}