{"Name":"Counterspell","School":"abjuration","Level":3,"PageContent":"Source: Player\u0027s Handbook\n3rd-level abjuration\nCasting Time: 1 reaction, which you take when you see a creature within 60 feet of you casting a spell\nRange: 60 feet\nComponents: S\nDuration: Instantaneous\nYou attempt to interrupt a creature in the process of casting a spell. If the creature is casting a spell of 3rd level or lower, its spell fails and has no effect. If it is casting a spell of 4th level or higher, make an ability check using your spellcasting ability. The DC equals 10 \u002B the spell\u2019s level. On a success, the creature\u2019s spell fails and has no effect.\nAt Higher Levels. When you cast this spell using a spell slot of 4th level or higher, the interrupted spell has no effect if its level is less than or equal to the level of the spell slot you used.\nSpell Lists. Sorcerer, Warlock, Wizard","InLists":["Sorcerer","Warlock","Wizard"],"Source":"Player\u0027s Handbook","CastingTime":"1 reaction, which you take when you see a creature within 60 feet of you casting a spell","Components":["S"],"Range":"60 feet","Duration":"instantaneous"}