{"Id":66,"Name":"Create or Destroy Water","School":"transmutation","Level":1,"PageContent":"Source: Player\u0027s Handbook\n1st-level transmutation\nCasting Time: 1 action\nRange: 30 feet\nComponents: V, S, M (a drop of water if creating water or a few grains of sand if destroying it)\nDuration: Instantaneous\nYou either create or destroy water.\nCreate Water. You create up to 10 gallons of clean water within range in an open container. Alternatively, the water falls as rain in a 30-foot cube within range, extinguishing exposed flames in the area.\nDestroy Water. You destroy up to 10 gallons of water in an open container within range. Alternatively, you destroy fog in a 30-foot cube within range.\nAt Higher Levels. When you cast this spell using a spell slot of 2nd level or higher, you create or destroy 10 additional gallons of water, or the size of the cube increases by 5 feet, for each slot level above 1st.\nSpell Lists. Cleric, Druid","InLists":["Cleric","Druid"],"Source":"Player\u0027s Handbook","CastingTime":"1 action","Components":["V","S","M (a drop of water if creating water or a few grains of sand if destroying it)"],"Range":"30 feet","Duration":"instantaneous"}