{"Id":355,"Name":"Creation","School":"illusion","Level":5,"PageContent":"Source: Player\u0027s Handbook\n5th-level illusion\nCasting Time: 1 minute\nRange: 30 feet\nComponents: V, S, M (a tiny piece of matter of the same type of the item you plan to create)\nDuration: Special\nYou pull wisps of shadow material from the Shadowfell to create a nonliving object of vegetable matter within range: soft goods, rope, wood, or something similar. You can also use this spell to create mineral objects such as stone, crystal, or metal. The object created must be no larger than a 5-foot cube, and the object must be of a form and material that you have seen before.\nThe duration depends on the object\u2019s material. If the object is composed of multiple materials, use the shortest duration.\n\n\nMaterial\nDuration\n\n\nVegetable matter\n1 day\n\n\nStone, crystal\n12 hours\n\n\nPrecious metals\n1 hour\n\n\nGems\n10 minutes\n\n\nAdamantine, Mithral\n1 minute\n\n\nUsing any material created by this spell as another spell\u2019s material component causes that spell to fail.\nAt Higher Levels. When you cast this spell using a spell slot of 6th level or higher, the cube increases by 5 feet for each slot level above 5th.\nSpell Lists. Artificer, Sorcerer, Wizard","InLists":["Artificer","Sorcerer","Wizard"],"Source":"Player\u0027s Handbook","CastingTime":"1 minute","Components":["V","S","M (a tiny piece of matter of the same type of the item you plan to create)"],"Range":"30 feet","Duration":"special"}