{"Name": "Dancing Lights", "School": "evocation", "Level": 0, "PageContent": "Source: Player's Handbook\nEvocation cantrip\nCasting Time: 1 action\nRange: 120 feet\nComponents: V, S, M (a bit of phosphorus or wychwood, or a glowworm)\nDuration: Concentration, up to 1 minute\nYou create up to four torch-sized lights within range, making them appear as torches, lanterns, or glowing orbs that hover in the air for the duration. You can also combine the four lights into one glowing vaguely humanoid form of Medium size. Whichever form you choose, each light sheds dim light in a 10-foot radius.\nAs a bonus action on your turn, you can move the lights up to 60 feet to a new spot within range. A light must be within 20 feet of another light created by this spell, and a light winks out if it exceeds the spell\u2019s range.\nSpell Lists. Artificer, Bard, Sorcerer, Wizard", "InLists": ["Artificer", "Bard", "Sorcerer", "Wizard"], "Source": "Player's Handbook", "CastingTime": "1 action", "Components": ["V", "S", "M (a bit of phosphorus or wychwood", "or a glowworm)"], "Range": "120 feet", "Duration": "concentration, up to 1 minute", "Id": 108}