{"Name": "Dispel Evil and Good", "School": "abjuration", "Level": 5, "PageContent": "Source: Player's Handbook\n5th-level abjuration\nCasting Time: 1 action\nRange: Self\nComponents: V, S, M (holy water or powdered silver and iron)\nDuration: Concentration, up to 1 minute\nShimmering energy surrounds and protects you from fey, undead, and creatures originating from beyond the Material Plane. For the duration, celestials, elementals, fey, fiends, and undead have disadvantage on attack rolls against you. You can end the spell early by using either of the following special functions.\n\nBreak Enchantment. As your action, you touch a creature you can reach that is charmed, frightened, or possessed by a celestial, an elemental, a fey, a fiend, or an undead. The creature you touch is no longer charmed, frightened, or possessed by such creatures.\n\n\nDismissal. As your action, make a melee spell attack against a celestial, an elemental, a fey, a fiend, or an undead you can reach. On a hit, you attempt to drive the creature back to its home plane. The creature must succeed on a Charisma saving throw or be sent back to its home plane (if it isn\u2019t there already). If they are already on their home plane, undead are sent to the Shadowfell, and fey are sent to the Feywild.\n\nSpell Lists. Cleric, Paladin", "InLists": ["Cleric", "Paladin"], "Source": "Player's Handbook", "CastingTime": "1 action", "Components": ["V", "S", "M (holy water or powdered silver and iron)"], "Range": "self", "Duration": "concentration, up to 1 minute", "Id": 127}