{"Name": "Dragon's Breath", "School": "transmutation", "Level": 2, "PageContent": "Source: Xanathar's Guide to Everything\n2nd-level transmutation\nCasting Time: 1 bonus action\nRange: Touch\nComponents: V, S, M (a hot pepper)\nDuration: Concentration, up to 1 minute\nYou touch one willing creature and imbue it with the power to spew magical energy from its mouth, provided it has one. Choose acid, cold, fire, lightning, or poison. Until the spell ends, the creature can use an action to exhale energy of the chosen type in a 15-foot cone. Each creature in that area must make a Dexterity saving throw, taking 3d6 damage of the chosen type on a failed save, or half as much damage on a successful one.\nAt Higher Levels. When you cast this spell using a spell slot of 3rd level or higher, the damage increases by 1d6 for each slot level above 2nd.\nSpell Lists. Sorcerer, Wizard", "InLists": ["Sorcerer", "Wizard"], "Source": "Xanathar's Guide to Everything", "CastingTime": "1 bonus action", "Components": ["V", "S", "M (a hot pepper)"], "Range": "touch", "Duration": "concentration, up to 1 minute", "Id": 138}