{"Id":8,"Name":"Druidcraft","School":"transmutation","Level":0,"PageContent":"Source: Player\u0027s Handbook\nTransmutation cantrip\nCasting Time: 1 action\nRange: 30 feet\nComponents: V, S\nDuration: Instantaneous\nWhispering to the spirits of nature, you create one of the following effects within range:\n\nYou create a tiny, harmless sensory effect that predicts what the weather will be at your location for the next 24 hours. The effect might manifest as a golden orb for clear skies, a cloud for rain, falling snowflakes for snow, and so on. This effect persists for 1 round.\n\n\nYou instantly make a flower blossom, a seed pod open, or a leaf bud bloom.\n\n\nYou create an instantaneous, harmless sensory effect, such as falling leaves, a puff of wind, the sound of a small animal, or the faint odor of skunk. The effect must fit in a 5-foot cube.\n\n\nYou instantly light or snuff out a candle, a torch, or a small campfire.\n\nSpell Lists. Druid","InLists":["Druid"],"Source":"Player\u0027s Handbook","CastingTime":"1 action","Components":["V","S"],"Range":"30 feet","Duration":"instantaneous"}