{"Id":75,"Name":"Earth Tremor","School":"evocation","Level":1,"PageContent":"Source: Xanathar\u0027s Guide to Everything/Elemental Evil Player\u0027s Companion\n1st-level evocation\nCasting Time: 1 action\nRange: Self (10-foot radius)\nComponents: V, S\nDuration: Instantaneous\nYou cause a tremor in the ground in a 10-foot radius. Each creature other than you in that area must make a Dexterity saving throw. On a failed save, a creature takes 1d6 bludgeoning damage and is knocked prone. If the ground in that area is loose earth or stone, it becomes difficult terrain until cleared.\nAt Higher Levels. When you cast this spell using a spell slot of 2nd level or higher, the damage increases by 1d6 for each slot level above 1st.\nSpell Lists. Bard, Druid, Sorcerer, Wizard","InLists":["Bard","Druid","Sorcerer","Wizard"],"Source":"Xanathar\u0027s Guide to Everything/Elemental Evil Player\u0027s Companion","CastingTime":"1 action","Components":["V","S"],"Range":"self (10-foot radius)","Duration":"instantaneous"}