{"Id":152,"Name":"Enthrall","School":"enchantment","Level":2,"PageContent":"Source: Player\u0027s Handbook\n2nd-level enchantment\nCasting Time: 1 action\nRange: 60 feet\nComponents: V, S\nDuration: 1 minute\nYou weave a distracting string of words, causing creatures of your choice that you can see within range and that can hear you to make a Wisdom saving throw. Any creature that can\u2019t be charmed succeeds on this saving throw automatically, and if you or your companions are fighting a creature, it has advantage on the save. On a failed save, the target has disadvantage on Wisdom (Perception) checks made to perceive any creature other than you until the spell ends or until the target can no longer hear you. The spell ends if you are incapacitated or can no longer speak.\nSpell Lists. Bard, Warlock","InLists":["Bard","Warlock"],"Source":"Player\u0027s Handbook","CastingTime":"1 action","Components":["V","S"],"Range":"60 feet","Duration":"1 minute","WikidotLink":"http://dnd5e.wikidot.com//spell:enthrall"}