{"Id":238,"Name":"Flame Arrows","School":"transmutation","Level":3,"PageContent":"Source: Xanathar\u0027s Guide to Everything\n3rd-level transmutation\nCasting Time: 1 action\nRange: Touch\nComponents: V, S\nDuration: Concentration, up to 1 hour\nYou touch a quiver containing arrows or bolts. When a target is hit by a ranged weapon attack using a piece of ammunition drawn from the quiver, the target takes an extra 1d6 fire damage. The spell\u2019s magic ends on the piece of ammunition when it hits or misses, and the spell ends when twelve pieces of ammunition have been drawn from the quiver.\nAt Higher Levels. When you cast this spell using a spell slot of 4th level or higher, the number of pieces of ammunition you can affect with this spell increases by two for each slot level above 3rd.\nSpell Lists. Druid, Ranger, Sorcerer, Wizard, Artificer","InLists":["Druid","Ranger","Sorcerer","Wizard","Artificer"],"Source":"Xanathar\u0027s Guide to Everything","CastingTime":"1 action","Components":["V","S"],"Range":"touch","Duration":"concentration, up to 1 hour","WikidotLink":"http://dnd5e.wikidot.com//spell:flame-arrows"}