{"Id":158,"Name":"Fortune\u0027s Favor","School":"divination","Level":2,"PageContent":"Source: Explorer\u0027s Guide to Wildemount\n2nd-level divination (dunamancy)\nCasting Time: 1 minute\nRange: 60 feet\nComponents: V, S, M (a white pearl worth at least 100 gp, which the spell consumes)\nDuration: 1 hour\nYou impart latent luck to yourself or one willing creature you can see within range. When the chosen creature makes an attack roll, an ability check, or a saving throw before the spell ends, it can dismiss this spell on itself to roll an additional d20 and choose which of the d20s to use. Alternatively, when an attack roll is made against the chosen creature, it can dismiss this spell on itself to roll a d20 and choose which of the d20s to use, the one it rolled or the one the attacker rolled.\nIf the original d20 roll has advantage or disadvantage, the creature rolls the additional d20 after advantage or disadvantage has been applied to the original roll.\nAt Higher Levels. When you cast this spell using a spell slot of 3rd level or higher, you can target one additional creature for each slot level above 2nd.\nSpell Lists. Wizard (Dunamancy)","InLists":["Wizard (Dunamancy)"],"Source":"Explorer\u0027s Guide to Wildemount","CastingTime":"1 minute","Components":["V","S","M (a white pearl worth at least 100 gp","which the spell consumes)"],"Range":"60 feet","Duration":"1 hour"}