{"Id":240,"Name":"Freedom of the Waves (HB)","School":"conjuration","Level":3,"PageContent":"Source: Tal\u0027Dorei Campaign Setting Reborn\n3rd-level conjuration\nCasting Time: 1 action\nRange: 120 feet\nComponents: V, S, M (a strand of wet hair)\nDuration: Instantaneous\nYou conjure a deluge of seawater in a 15-foot-radius, 10-foot-tall cylinder centered on a point within range. This water takes the form of a tidal wave, a whirlpool, a waterspout, or another form of your choice. Each creature in the area must succeed on a Strength saving throw against your spell save DC or take 2d8 bludgeoning damage and fall prone. You can choose a number of creatures equal to your spellcasting modifier (minimum of 1) to automatically succeed on this saving throw.\nIf you are within the spell\u2019s area, as part of the action you use to cast the spell, you can vanish into the deluge and teleport to an unoccupied space that you can see within the spell\u2019s area.\nSpell Lists. Druid, Ranger, Sorcerer","InLists":["Druid","Ranger","Sorcerer"],"Source":"Tal\u0027Dorei Campaign Setting Reborn","CastingTime":"1 action","Components":["V","S","M (a strand of wet hair)"],"Range":"120 feet","Duration":"instantaneous","WikidotLink":"http://dnd5e.wikidot.com//spell:freedom-of-the-waves"}