{"Id":12,"Name":"Friends","School":"enchantment","Level":0,"PageContent":"Source: Player\u0027s Handbook\nEnchantment cantrip\nCasting Time: 1 action\nRange: Self\nComponents: S, M (a small amount of makeup applied to the face as this spell is cast)\nDuration: Concentration, up to 1 minute\nFor the duration, you have advantage on all Charisma checks directed at one creature of your choice that isn\u0027t hostile toward you. When the spell ends, the creature realizes that you used magic to influence its mood and becomes hostile toward you. A creature prone to violence might attack you. Another creature might seek retribution in other ways (at the DM\u0027s discretion), depending on the nature of your interaction with it.\nSpell Lists. Bard, Sorcerer, Warlock, Wizard","InLists":["Bard","Sorcerer","Warlock","Wizard"],"Source":"Player\u0027s Handbook","CastingTime":"1 action","Components":["S","M (a small amount of makeup applied to the face as this spell is cast)"],"Range":"self","Duration":"concentration, up to 1 minute"}