{"Id":239,"Name":"Galder\u0027s Tower","School":"conjuration","Level":3,"PageContent":"Source: Lost Laboratory of Kwalish\n3rd-level conjuration\nCasting Time: 10 minutes\nRange: 30 feet\nComponents: V, S, M (a fragment of stone, wood, or other building material)\nDuration: 24 hours\nYou conjure a two-story tower made of stone, wood, or similar suitably sturdy materials. The tower can be round or square in shape. Each level of the tower is 10 feet tall and has an area of up to 100 square feet. Access between levels consists of a simple ladder and hatch. Each level takes one of the following forms, chosen by you when you cast the spell:\n\nA bedroom with a bed, chairs, chest, and magical fireplace\n\n\nA study with desks, books, bookshelves, parchments, ink, and ink pens\n\n\nA dining space with a table, chairs, magical fireplace, containers, and cooking utensils\n\n\nA lounge with couches, armchairs, side tables and footstools\n\n\nA washroom with toilets, washtubs, a magical brazier, and sauna benches\n\n\nAn observatory with a telescope and maps of the night sky\n\n\nAn unfurnished, empty room\n\nThe interior of the tower is warm and dry, regardless of conditions outside. Any equipment or furnishings conjured with the tower dissipate into smoke if removed from it. At the end of the spell\u2019s duration, all creatures and objects within the tower that were not created by the spell appear safely outside on the ground, and all traces of the tower and its furnishings disappear.\nYou can cast this spell again while it is active to maintain the tower\u2019s existence for another 24 hours. You can create a permanent tower by casting this spell in the same location and with the same configuration every day for one year.\nAt Higher Levels. When you cast this spell using a spell slot of 4th level or higher, the tower can have one additional story for each slot level beyond 3rd.\nSpell Lists. Wizard","InLists":["Wizard"],"Source":"Lost Laboratory of Kwalish","CastingTime":"10 minutes","Components":["V","S","M (a fragment of stone","wood","or other building material)"],"Range":"30 feet","Duration":"24 hours"}