{"Id":366,"Name":"Geas","School":"enchantment","Level":5,"PageContent":"Source: Player\u0027s Handbook\n5th-level enchantment\nCasting Time: 1 minute\nRange: 60 feet\nComponents: V\nDuration: 30 days\nYou place a magical command on a creature that you can see within range, forcing it to carry out some service or refrain from some action or course of activity as you decide.\nIf the creature can understand you, it must succeed on a Wisdom saving throw or become charmed by you for the duration. While the creature is charmed by you, it takes 5d10 psychic damage each time it acts in a manner directly counter to your instructions, but no more than once each day. A creature that can\u2019t understand you is unaffected by the spell.\nYou can issue any command you choose, short of an activity that would result in certain death. Should you issue a suicidal command, the spell ends. You can end the spell early by using an action to dismiss it. A Remove Curse, Greater Restoration, or Wish spell also ends it.\nAt Higher Levels. When you cast this spell using a spell slot of 7th or 8th level, the duration is 1 year. When you cast this spell using a spell slot of 9th level, the spell lasts until it is ended by one of the spells mentioned above.\nSpell Lists. Bard, Cleric, Druid, Paladin, Wizard","InLists":["Bard","Cleric","Druid","Paladin","Wizard"],"Source":"Player\u0027s Handbook","CastingTime":"1 minute","Components":["V"],"Range":"60 feet","Duration":"30 days"}