{"Name": "Greater Restoration", "School": "abjuration", "Level": 5, "PageContent": "Source: Player's Handbook\n5th-level abjuration\nCasting Time: 1 action\nRange: Touch\nComponents: V, S, M (diamond dust worth at least 100 gp, which the spell consumes)\nDuration: Instantaneous\nYou imbue a creature you touch with positive energy to undo a debilitating effect. You can reduce the target\u2019s exhaustion level by one, or end one of the following effects on the target:\n\nOne effect that charmed or petrified the target\n\n\nOne curse, including the target\u2019s attunement to a cursed magic item\n\n\nAny reduction to one of the target\u2019s ability scores\n\n\nOne effect reducing the target\u2019s hit point maximum\n\nSpell Lists. Artificer, Bard, Cleric, Druid, Ranger", "InLists": ["Artificer", "Bard", "Cleric", "Druid", "Ranger"], "Source": "Player's Handbook", "CastingTime": "1 action", "Components": ["V", "S", "M (diamond dust worth at least 100 gp", "which the spell consumes)"], "Range": "touch", "Duration": "instantaneous", "Id": 220}