{"Id":14,"Name":"Green-Flame Blade","School":"evocation","Level":0,"PageContent":"Source: Tasha\u0027s Cauldron of Everything/Sword Coast Adventurer\u0027s Guide\nEvocation cantrip\nCasting Time: 1 action\nRange: Self (5-foot radius)\nComponents: S, M (a melee weapon worth at least 1 sp)\nDuration: Instantaneous\nYou brandish the weapon used in the spell\u2019s casting and make a melee attack with it against one creature within 5 feet of you. On a hit, the target suffers the weapon attack\u2019s normal effects, and you can cause green fire to leap from the target to a different creature of your choice that you can see within 5 feet of it. The second creature takes fire damage equal to your spellcasting ability modifier.\nAt Higher Levels. At 5th level, the melee attack deals an extra 1d8 fire damage to the target on a hit, and the fire damage to the second creature increases to 1d8 \u002B your spellcasting ability modifier. Both damage rolls increase by 1d8 at 11th level (2d8 and 2d8) and 17th level (3d8 and 3d8).\nSpell Lists. Artificer, Sorcerer, Warlock, Wizard","InLists":["Artificer","Sorcerer","Warlock","Wizard"],"Source":"Tasha\u0027s Cauldron of Everything/Sword Coast Adventurer\u0027s Guide","CastingTime":"1 action","Components":["S","M (a melee weapon worth at least 1 sp)"],"Range":"self (5-foot radius)","Duration":"instantaneous"}