{"Name": "Guardian of Nature", "School": "transmutation", "Level": 4, "PageContent": "Source: Xanathar's Guide to Everything\n4th-level transmutation\nCasting Time: 1 bonus action\nRange: Self\nComponents: V\nDuration: Concentration, up to 1 minute\nA nature spirit answers your call and transforms you into a powerful guardian. The transformation lasts until the spell ends. You choose one of the following forms to assume: Primal Beast or Great Tree.\nPrimal Beast. Bestial fur covers your body, your facial features become feral, and you gain the following benefits:\n\nYour walking speed increases by 10 feet.\n\n\nYou gain darkvision with a range of 120 feet.\n\n\nYou make Strength-based attack rolls with advantage.\n\n\nYour melee weapon attacks deal an extra 1d6 force damage on a hit.\n\nGreat Tree. Your skin appears barky, leaves sprout from your hair, and you gain the following benefits:\n\nYou gain 10 temporary hit points.\n\n\nYou make Constitution saving throws with advantage.\n\n\nYou make Dexterity and Wisdom-based attack rolls with advantage.\n\n\nWhile you are on the ground, the ground within 15 feet of you is difficult terrain for your enemies.\n\nSpell Lists. Druid, Ranger", "InLists": ["Druid", "Ranger"], "Source": "Xanathar's Guide to Everything", "CastingTime": "1 bonus action", "Components": ["V"], "Range": "self", "Duration": "concentration, up to 1 minute", "Id": 223}