{"Id":16,"Name":"Gust","School":"transmutation","Level":0,"PageContent":"Source: Xanathar\u0027s Guide to Everything\nTransmutation cantrip\nCasting Time: 1 action\nRange: 30 feet\nComponents: V, S\nDuration: Instantaneous\nYou seize the air and compel it to create one of the following effects at a point you can see within range:\n\nOne Medium or smaller creature that you choose must succeed on a Strength saving throw or be pushed up to 5 feet away from you.\n\n\nYou create a small blast of air capable of moving one object that is neither held nor carried and that weighs no more than 5 pounds. The object is pushed up to 10 feet away from you. It isn\u2019t pushed with enough force to cause damage.\n\n\nYou create a harmless sensory affect using air, such as causing leaves to rustle, wind to slam shutters shut, or your clothing to ripple in a breeze.\n\nSpell Lists. Druid, Sorcerer, Wizard","InLists":["Druid","Sorcerer","Wizard"],"Source":"Xanathar\u0027s Guide to Everything","CastingTime":"1 action","Components":["V","S"],"Range":"30 feet","Duration":"instantaneous"}