{"Name": "Healing Spirit", "School": "conjuration", "Level": 2, "PageContent": "Source: Xanathar's Guide to Everything\n2nd-level conjuration\nCasting Time: 1 bonus action\nRange: 60 feet\nComponents: V, S\nDuration: Concentration, up to 1 minute\nYou call forth a nature spirit to soothe the wounded. The intangible spirit appears in a space that is a 5-foot cube you can see within range. The spirit looks like a transparent beast or fey (your choice).\nUntil the spell ends, whenever you or a creature you can see moves into the spirits space for the first time on a turn or starts its turn there, you can cause the spirit to restore 1d6 hit points to that creature (no action required). The spirit can\u2019t heal constructs or undead.\nAs a bonus action on your turn, you can move the Spirit up to 30 feet to a space you can see. The spirit can heal a number of times equal to 1 + your spellcasting ability modifier (minimum of twice). After healing that number of times, the spirit disappears.\nAt Higher Levels. When you cast this spell using a spell slot of 3rd level or higher, the healing increases 1d6 for each slot level above 2nd.\nSpell Lists. Druid, Ranger", "InLists": ["Druid", "Ranger"], "Source": "Xanathar's Guide to Everything", "CastingTime": "1 bonus action", "Components": ["V", "S"], "Range": "60 feet", "Duration": "concentration, up to 1 minute", "Id": 235}