{"Name":"Heroes\u0027 Feast","School":"conjuration","Level":6,"PageContent":"Source: Player\u0027s Handbook\n6th-level conjuration\nCasting Time: 10 minutes\nRange: 30 feet\nComponents: V, S, M (a gem-encrusted bowl worth at least 1,000 gp, which the spell consumes)\nDuration: Instantaneous\nYou bring forth a great feast, including magnificent food and drink. The feast takes 1 hour to consume and disappears at the end of that time, and the beneficial effects don\u2019t set in until this hour is over. Up to twelve creatures can partake of the feast.\nA creature that partakes of the feast gains several benefits. The creature is cured of all diseases and poison, becomes immune to poison and being frightened, and makes all Wisdom saving throws with advantage. Its hit point maximum also increases by 2d10, and it gains the same number of hit points. These benefits last for 24 hours.\nSpell Lists. Bard, Cleric, Druid","InLists":["Bard","Cleric","Druid"],"Source":"Player\u0027s Handbook","CastingTime":"10 minutes","Components":["V","S","M (a gem-encrusted bowl worth at least 1,000 gp","which the spell consumes)"],"Range":"30 feet","Duration":"instantaneous"}