{"Name": "Hunter's Mark", "School": "divination", "Level": 1, "PageContent": "Source: Player's Handbook\n1st-level divination\nCasting Time: 1 bonus action\nRange: 90 feet\nComponents: V\nDuration: Concentration, up to 1 hour\nYou choose a creature you can see within range and mystically mark it as your quarry. Until the spell ends, you deal an extra 1d6 damage to the target whenever you hit it with a weapon attack, and you have advantage on any Wisdom (Perception) or Wisdom (Survival) check you make to find it.\nIf the target drops to 0 hit points before this spell ends, you can use a bonus action on a subsequent turn of yours to mark a new creature.\nAt Higher Levels. When you cast this spell using a spell slot of 3rd or 4th level, you can maintain your concentration on the spell for up to 8 hours. When you use a spell slot of 5th level or higher, you can maintain your concentration on the spell for up to 24 hours.\nSpell Lists. Ranger", "InLists": ["Ranger"], "Source": "Player's Handbook", "CastingTime": "1 bonus action", "Components": ["V"], "Range": "90 feet", "Duration": "concentration, up to 1 hour", "Id": 247}