{"Name":"Hypnotic Pattern","School":"illusion","Level":3,"PageContent":"Source: Player\u0027s Handbook\n3rd-level illusion\nCasting Time: 1 action\nRange: 120 feet\nComponents: S, M (a glowing stick of incense or a crystal vial filled with phosphorescent material)\nDuration: Concentration, up to 1 minute\nYou create a twisting pattern of colors that weaves through the air inside a 30-foot cube within range. The pattern appears for a moment and vanishes. Each creature in the area who sees the pattern must make a Wisdom saving throw. On a failed save, the creature becomes charmed for the duration. While charmed by this spell, the creature is incapacitated and has a speed of 0.\nThe spell ends for an affected creature if it takes any damage or if someone else uses an action to shake the creature out of its stupor.\nSpell Lists. Bard, Sorcerer, Warlock, Wizard","InLists":["Bard","Sorcerer","Warlock","Wizard"],"Source":"Player\u0027s Handbook","CastingTime":"1 action","Components":["S","M (a glowing stick of incense or a crystal vial filled with phosphorescent material)"],"Range":"120 feet","Duration":"concentration, up to 1 minute"}