{"Id":95,"Name":"Ice Knife","School":"conjuration","Level":1,"PageContent":"Source: Xanathar\u0027s Guide to Everything\n1st-level conjuration\nCasting Time: 1 action\nRange: 60 feet\nComponents: S, M (a drop of water or piece of ice)\nDuration: Instantaneous\nYou create a shard of ice and fling it at one creature within range. Make a ranged spell attack against the target. On a hit, the target takes 1d10 piercing damage. Hit or miss, the shard then explodes. The target and each creature within 5 feet of the point where the ice exploded must succeed on a Dexterity saving throw or take 2d6 cold damage.\nAt Higher Levels. When you cast this spell using a spell slot of 2nd level or higher, the cold damage increases by 1d6 for each slot level above 1st.\nSpell Lists. Druid, Sorcerer, Wizard","InLists":["Druid","Sorcerer","Wizard"],"Source":"Xanathar\u0027s Guide to Everything","CastingTime":"1 action","Components":["S","M (a drop of water or piece of ice)"],"Range":"60 feet","Duration":"instantaneous"}