{"Name":"Ice Storm","School":"evocation","Level":4,"PageContent":"Source: Player\u0027s Handbook\n4th-level evocation\nCasting Time: 1 action\nRange: 300 feet\nComponents: V, S, M (a pinch of dust and a few drops of water)\nDuration: Instantaneous\nA hail of rock-hard ice pounds to the ground in a 20-foot-radius, 40-foot-high cylinder centered on a point within range. Each creature in the cylinder must make a Dexterity saving throw. A creature takes 2d8 bludgeoning damage and 4d6 cold damage on a failed save, or half as much damage on a successful one.\nHailstones turn the storm\u2019s area of effect into difficult terrain until the end of your next turn.\nAt Higher Levels. When you cast this spell using a spell slot of 5th level or higher, the bludgeoning damage increases by 1d8 for each slot level above 4th.\nSpell Lists. Druid, Sorcerer, Wizard","InLists":["Druid","Sorcerer","Wizard"],"Source":"Player\u0027s Handbook","CastingTime":"1 action","Components":["V","S","M (a pinch of dust and a few drops of water)"],"Range":"300 feet","Duration":"instantaneous"}