{"Id":96,"Name":"Identify","School":"divination","Level":1,"PageContent":"Source: Player\u0027s Handbook\n1st-level divination (ritual)\nCasting Time: 1 minute\nRange: Touch\nComponents: V, S, M (a pearl worth at least 100 gp and an owl feather)\nDuration: Instantaneous\nYou choose one object that you must touch throughout the casting of the spell. If it is a magic item or some other magic-imbued object, you learn its properties and how to use them, whether it requires attunement to use, and how many charges it has, if any. You learn whether any spells are affecting the item and what they are. If the item was created by a spell, you learn which spell created it.\nIf you instead touch a creature throughout the casting, you learn what spells, if any, are currently affecting it.\nSpell Lists. Artificer, Bard, Wizard","InLists":["Artificer","Bard","Wizard"],"Source":"Player\u0027s Handbook","CastingTime":"1 minute","Components":["V","S","M (a pearl worth at least 100 gp and an owl feather)"],"Range":"touch","Duration":"instantaneous"}