{"Id":248,"Name":"Intellect Fortress","School":"abjuration","Level":3,"PageContent":"Source: Tasha\u0027s Cauldron of Everything\n3rd-level abjuration\nCasting Time: 1 action\nRange: 30 feet\nComponents: V\nDuration: Concentration, up to 1 hour\nFor the duration, you or one willing creature you can see within range has resistance to psychic damage, as well as advantage on Intelligence, Wisdom, and Charisma saving throws.\nAt Higher Levels. When you cast this spell using a spell slot of 4th level or higher, you can target one additional creature for each slot level above 3rd. The creatures must be within 30 feet of each other when you target them.\nSpell Lists: Artificer, Bard (Optional), Sorcerer (Optional), Warlock (Optional), Wizard (Optional)","InLists":["Artificer","Bard (Optional)","Sorcerer (Optional)","Warlock (Optional)","Wizard (Optional)"],"Source":"Tasha\u0027s Cauldron of Everything","CastingTime":"1 action","Components":["V"],"Range":"30 feet","Duration":"concentration, up to 1 hour","WikidotLink":"http://dnd5e.wikidot.com//spell:intellect-fortress"}