{"Name":"Mage Hand","School":"conjuration","Level":0,"PageContent":"Source: Player\u0027s Handbook\nConjuration cantrip\nCasting Time: 1 action\nRange: 30 feet\nComponents: V, S\nDuration: 1 minute\nA spectral, floating hand appears at a point you choose within range. The hand lasts for the duration or until you dismiss it as an action. The hand vanishes if it is ever more than 30 feet away from you or if you cast this spell again.\nYou can use your action to control the hand. You can use the hand to manipulate an object, open an unlocked door or container, stow or retrieve an item from an open container, or pour the contents out of a vial. You can move the hand up to 30 feet each time you use it.\nThe hand can\u2019t attack, activate magical items, or carry more than 10 pounds.\nSpell Lists. Artificer, Bard, Sorcerer, Warlock, Wizard","InLists":["Artificer","Bard","Sorcerer","Warlock","Wizard"],"Source":"Player\u0027s Handbook","CastingTime":"1 action","Components":["V","S"],"Range":"30 feet","Duration":"1 minute"}