{"Name":"Mordenkainen\u0027s Sword","School":"evocation","Level":7,"PageContent":"Source: Player\u0027s Handbook\n7th-level evocation\nCasting Time: 1 action\nRange: 60 feet\nComponents: V, S, M (a miniature platinum sword with a grip and pommel of copper and zinc, worth 250 gp)\nDuration: Concentration, up to 1 minute\nYou create a sword-shaped plane of force that hovers within range. It lasts for the duration.\nWhen the sword appears, you make a melee spell attack against a target of your choice within 5 feet of the sword. On a hit. the target takes 3d10 force damage. Until the spell ends, you can use a bonus action on each of your turns to move the sword up to 20 feet to a spot you can see and repeat this attack against the same target or a different one.\nSpell Lists. Bard, Wizard","InLists":["Bard","Wizard"],"Source":"Player\u0027s Handbook","CastingTime":"1 action","Components":["V","S","M (a miniature platinum sword with a grip and pommel of copper and zinc","worth 250 gp)"],"Range":"60 feet","Duration":"concentration, up to 1 minute"}