{"Name":"Nystul\u0027s Magic Aura","School":"illusion","Level":2,"PageContent":"Source: Player\u0027s Handbook\n2nd-level illusion\nCasting Time: 1 action\nRange: Touch\nComponents: V, S, M (a small square of silk)\nDuration: 24 hours\nYou place an illusion on a creature or an object you touch so that divination spells reveal false information about it. The target can be a willing creature or an object that isn\u2019t being carried or worn by another creature.\nWhen you cast the spell, choose one or both of the following effects. The effect lasts for the duration. If you cast this spell on the same creature or object every day for 30 days, placing the same effect on it each time, the illusion lasts until it is dispelled.\nFalse Aura. You change the way the target appears to spells and magical effects, such as Detect Magic, that detect magical auras. You can make a nonmagical object appear magical, a magical object appear nonmagical, or change the object\u2019s magical aura so that it appears to belong to a specific school of magic that you choose. When you use this effect on an object, you can make the false magic apparent to any creature that handles the item.\nMask. You change the way the target appears to spells and magical effects that detect creature types, such as a paladin\u2019s Divine Sense or the trigger of a symbol spell. You choose a creature type and other spells and magical effects treat the target as if it were a creature of that type or of that alignment.\nSpell Lists. Wizard","InLists":["Wizard"],"Source":"Player\u0027s Handbook","CastingTime":"1 action","Components":["V","S","M (a small square of silk)"],"Range":"touch","Duration":"24 hours"}