{"Name": "Otto's Irresistible Dance", "School": "enchantment", "Level": 6, "PageContent": "Source: Player's Handbook\n6th-level enchantment\nCasting Time: 1 action\nRange: 30 feet\nComponents: V\nDuration: Concentration, up to 1 minute\nChoose one creature that you can see within range. The target begins a comic dance in place: shuffling, tapping its feet, and capering for the duration. Creatures that can\u2019t be charmed are immune to this spell.\nA dancing creature must use all its movement to dance without leaving its space and has disadvantage on Dexterity saving throws and attack rolls. While the target is affected by this spell, other creatures have advantage on attack rolls against it. As an action, a dancing creature makes a Wisdom saving throw to regain control of itself. On a successful save, the spell ends.\nSpell Lists. Bard, Wizard", "InLists": ["Bard", "Wizard"], "Source": "Player's Handbook", "CastingTime": "1 action", "Components": ["V"], "Range": "30 feet", "Duration": "concentration, up to 1 minute", "Id": 339}