{"Id":259,"Name":"Plant Growth","School":"transmutation","Level":3,"PageContent":"Source: Player\u0027s Handbook\n3rd-level transmutation\nCasting Time: 1 action or 8 hours\nRange: 150 feet\nComponents: V, S\nDuration: Instantaneous\nThis spell channels vitality into plants within a specific area. There are two possible uses for the spell, granting either immediate or long-term benefits.\nIf you cast this spell using 1 action, choose a point within range. All normal plants in a 100-foot radius centered on that point become thick and overgrown. A creature moving through the area must spend 4 feet of movement for every 1 foot it moves.\nYou can exclude one or more areas of any size within the spell\u2019s area from being affected.\nIf you cast this spell over 8 hours, you enrich the land. All plants in a half-mile radius centered on a point within range become enriched for 1 year. The plants yield twice the normal amount of food when harvested.\nSpell Lists. Bard, Druid, Ranger","InLists":["Bard","Druid","Ranger"],"Source":"Player\u0027s Handbook","CastingTime":"1 action or 8 hours","Components":["V","S"],"Range":"150 feet","Duration":"instantaneous"}