{"Name": "Raulothim's Psychic Lance", "School": "enchantment", "Level": 4, "PageContent": "Source: Fizban's Treasury of Dragons\n4th-level Enchantment\nCasting Time: 1 Action\nRange: 120ft\nComponents: V\nDuration: Instantaneous\nYou unleash a shimmering lance of psychic power from your forehead at a creature that you can see within range. Alternatively, you can utter a creature\u2019s name. If the named target is within range, it becomes the spell\u2019s target even if you can\u2019t see it. If the named target isn\u2019t within range, the lance dissipates without effect.\nThe target must make an Intelligence saving throw. On a failed save, the target takes 7d6 psychic damage and is incapacitated until the start of your next turn. On a successful save, the creature takes half as much damage and isn\u2019t incapacitated.\nAt Higher Levels. When you cast this spell using a spell slot of 5th level or higher, the damage increases by 1d6 for each slot level above 4th.\nSpell Lists. Bard, Sorcerer, Warlock, Wizard", "InLists": ["Bard", "Sorcerer", "Warlock", "Wizard"], "Source": "Fizban's Treasury of Dragons", "CastingTime": "1 action", "Components": ["V"], "Range": "120ft", "Duration": "instantaneous", "Id": 373}