{"Name": "Reincarnate", "School": "transmutation", "Level": 5, "PageContent": "Source: Player's Handbook\n5th-level transmutation\nCasting Time: 1 hour\nRange: Touch\nComponents: V, S, M (rare oils and unguents worth at least 1,000 gp, which the spell consumes)\nDuration: Instantaneous\nYou touch a dead humanoid or a piece of a dead humanoid. Provided that the creature has been dead no longer than 10 days, the spell forms a new adult body for it and then calls the soul to enter that body. If the target\u2019s soul isn\u2019t free or willing to do so, the spell fails.\nThe magic fashions a new body for the creature to inhabit, which likely causes the creature\u2019s race to change. The DM rolls a d100 and consults the following table to determine what form the creature takes when restored to life, or the DM chooses a form.\n\n\nReincarnation Table\n\n\nd100\nRace\n\n\n01-04\nDragonborn\n\n\n05-13\nDwarf, hill\n\n\n14-21\nDwarf, mountain\n\n\n22-25\nElf, dark\n\n\n26-34\nElf, high\n\n\n35-42\nElf, wood\n\n\n43-46\nGnome, forest\n\n\n47-52\nGnome, rock\n\n\n53-56\nHalf-elf\n\n\n57-60\nHalf-orc\n\n\n61-68\nHalfling, lightfoot\n\n\n69-76\nHalfling, stout\n\n\n77-96\nHuman\n\n\n97-00\nTiefling\n\n\nThe reincarnated creature recalls its former life and experiences. It retains the capabilities it had in its original form, except it exchanges its original race for the new one and changes its racial traits accordingly.\nSpell Lists. Druid", "InLists": ["Druid"], "Source": "Player's Handbook", "CastingTime": "1 hour", "Components": ["V", "S", "M (rare oils and unguents worth at least 1,000 gp", "which the spell consumes)"], "Range": "touch", "Duration": "instantaneous", "Id": 380}