{"Id":190,"Name":"Rime\u0027s Binding Ice","School":"evocation","Level":2,"PageContent":"Source: Fizban\u0027s Treasury of Dragons\n2nd-level Evocation\nCasting Time: 1 Action\nRange: Self (30-foot cone)\nComponents: S, M (a vial of meltwater)\nDuration: Instantaneous\nA burst of cold energy emanates from you in a 30-foot cone. Each creature in that area must make a Constitution saving throw. On a failed save, a creature takes 3d8 cold damage and is hindered by ice formations for 1 minute, or until it or another creature within reach of it uses an action to break away the ice. A creature hindered by ice has its speed reduced to 0. On a successful save, a creature takes half as much damage and isn\u2019t hindered by ice.\nAt Higher Levels. When you cast this spell using a spell slot of 3rd level or higher, increase the cold damage by 1d8 for each slot level above 2nd.\nSpell Lists. Sorcerer, Wizard","InLists":["Sorcerer","Wizard"],"Source":"Fizban\u0027s Treasury of Dragons","CastingTime":"1 action","Components":["S","M (a vial of meltwater)"],"Range":"self (30-foot cone)","Duration":"instantaneous"}