{"Name": "Scrying", "School": "divination", "Level": 5, "PageContent": "Source: Player's Handbook\n5th-level divination\nCasting Time: 10 minutes\nRange: Self\nComponents: V, S, M (a focus worth at least 1,000 gp, such as a crystal ball, a silver mirror, or a font filled with holy water)\nDuration: Concentration, up to 10 minutes\nYou can see and hear a particular creature you choose that is on the same plane of existence as you. The target must make a Wisdom saving throw, which is modified by how well you know the target and the sort of physical connection you have to it. If a target knows you\u2019re casting this spell, it can fail the saving throw voluntarily if it wants to be observed.\n\n\nKnowledge\nSave Modifier\n\n\nSecondhand (you have heard of the target)\n+5\n\n\nFirsthand (you have met the target)\n+0\n\n\nFamiliar (you know the target well)\n-5\n\n\n\n\nConnection\nSave Modifier\n\n\nLikeness or picture\n-2\n\n\nPossession or garment\n-4\n\n\nBody part, lock of hair, bit of nail, or the like\u2003\n-10\n\n\nOn a successful save, the target isn\u2019t affected, and you can\u2019t use this spell against it again for 24 hours.\nOn a failed save, the spell creates an invisible sensor within 10 feet of the target. You can see and hear through the sensor as if you w ere there. The sensor moves with the target, remaining within 10 feet of it for the duration. A creature that can see invisible objects sees the sensor as a luminous orb about the size of your fist.\nInstead of targeting a creature, you can choose a location you have seen before as the target of this spell. When you do, the sensor appears at that location and doesn\u2019t move.\nSpell Lists. Bard, Cleric, Druid, Warlock, Wizard", "InLists": ["Bard", "Cleric", "Druid", "Warlock", "Wizard"], "Source": "Player's Handbook", "CastingTime": "10 minutes", "Components": ["V", "S", "M (a focus worth at least 1,000 gp", "such as a crystal ball", "a silver mirror", "or a font filled with holy water)"], "Range": "self", "Duration": "concentration, up to 10 minutes", "Id": 393}