{"Name": "Shadow Of Moil", "School": "necromancy", "Level": 4, "PageContent": "Source: Xanathar's Guide to Everything\n4th-level necromancy\nCasting Time: 1 action\nRange: Self\nComponents: V, S, M (an undead eyeball encased in a gem worth at least 150 gp)\nDuration: Concentration, up to 1 minute\nFlame-like shadows wreathe your body until the spell ends, causing you to become heavily obscured to others. The shadows turn dim light within 10 feet of you into darkness, and bright light in the same area to dim light.\nUntil the spell ends, you have resistance to radiant damage. In addition, whenever a creature within 10 feet of you hits you with an attack, the shadows lash out at that creature, dealing it 2d8 necrotic damage.\nSpell Lists. Warlock", "InLists": ["Warlock"], "Source": "Xanathar's Guide to Everything", "CastingTime": "1 action", "Components": ["V", "S", "M (an undead eyeball encased in a gem worth at least 150 gp)"], "Range": "self", "Duration": "concentration, up to 1 minute", "Id": 400}