{"Name": "Summon Beast", "School": "conjuration", "Level": 2, "PageContent": "Source: Tasha's Cauldron of Everything\n2nd-level conjuration\nCasting Time: 1 action\nRange: 90 feet\nComponents: V, S, M (a feather, tuft of fur, and fish tail inside a gilded acorn worth at least 200 gp)\nDuration: Concentration, up to 1 hour\nYou call forth a bestial spirit. It manifests in an unoccupied space that you can see within range. This corporeal form uses the Bestial Spirit stat block. When you cast the spell, choose an environment: Air, Land, or Water. The creature resembles an animal of your choice that is native to the chosen environment, which determines certain traits in its stat block. The creature disappears when it drops to 0 hit points or when the spell ends.\nThe creature is an ally to you and your companions. In combat, the creature shares your initiative count, but it takes its turn immediately after yours. It obeys your verbal commands (no action required by you). If you don\u2019t issue any, it takes the Dodge action and uses its move to avoid danger.\nAt Higher Levels. When you cast this spell using a spell slot of 3rd level or higher, use the higher level where the spell\u2019s level appears in the stat block.\nSpell Lists. Druid, Ranger\n\n\nBestial Spirit\n\n\nSmall beast\n\n\nArmor Class: 11 + the level of the spell (natural armor)\n\n\nHit Points: 20 (Air only) or 30 (Land and Water only) + 5 for each spell level above 2nd\n\n\nSpeed: 30 ft., climb 30 ft. (Land only), fly 60 ft. (Air only), swim 30 ft. (Water only)\n\n\nSTR\nDEX\nCON\nINT\nWIS\nCHA\n\n\n18 (+4)\n11 (+0)\n16 (+3)\n4 (\u22124)\n14 (+2)\n5 (\u22123)\n\n\nSenses: darkvision 60 ft., passive Perception 12\n\n\nLanguages: understands the languages you speak\n\n\nChallenge: &#8212;\n\n\nProficiency Bonus: equals your bonus\n\n\nFlyby (Air Only). The beast doesn\u2019t provoke opportunity attacks when it flies out of an enemy\u2019s reach.\n\n\nPack Tactics (Land and Water Only). The beast has advantage on an attack roll against a creature if at least one of the beast\u2019s allies is within 5 feet of the creature and the ally isn\u2019t incapacitated.\n\n\nWater Breathing (Water Only). The beast can breathe only underwater.\n\n\nActions\n\n\nMultiattack. The beast makes a number of attacks equal to half this spell\u2019s level (rounded down).\n\n\nMaul. Melee Weapon Attack: your spell attack modifier to hit, reach 5 ft., one target. Hit: 1d8 + 4 + the spell\u2019s level piercing damage.", "InLists": ["Druid", "Ranger"], "Source": "Tasha's Cauldron of Everything", "CastingTime": "1 action", "Components": ["V", "S", "M (a feather", "tuft of fur", "and fish tail inside a gilded acorn worth at least 200 gp)"], "Range": "90 feet", "Duration": "concentration, up to 1 hour", "Id": 439}