{"Id":444,"Name":"Summon Fiend","School":"conjuration","Level":6,"PageContent":"Source: Tasha\u0027s Cauldron of Everything\n6th-level conjuration\nCasting Time: 1 action\nRange: 90 feet\nComponents: V, S, M (humanoid blood inside a ruby vial worth at least 600 gp)\nDuration: Concentration, up to 1 hour\nYou call forth a fiendish spirit. It manifests in an unoccupied space that you can see within range. This corporeal form uses the Fiendish Spirit stat block. When you cast the spell, choose Demon, Devil, or Yugoloth. The creature resembles a fiend of the chosen type, which determines certain traits in its stat block. The creature disappears when it drops to 0 hit points or when the spell ends.\nThe creature is an ally to you and your companions. In combat, the creature shares your initiative count, but it takes its turn immediately after yours. It obeys your verbal commands (no action required by you). If you don\u2019t issue any, it takes the Dodge action and uses its move to avoid danger.\nAt Higher Levels. When you cast this spell using a spell slot of 7th level or higher, use the higher level wherever the spell\u2019s level appears in the stat block.\nSpell Lists. Warlock (Optional), Wizard (Optional)\nFiendish Spirit\nLarge fiend\nArmor Class: 12 \u002B the level of the spell (natural armor)\nHit Points: 50 (Demon only) or 40 (Devil only) or 60 (Yugoloth only) \u002B 15 for each spell level above 6th\nSpeed: 40 ft., climb 40 ft. (Demon only), fly 60 ft. (Devil only)\nSTR\nDEX\nCON\nINT\nWIS\nCHA\n13 (\u002B1)\n16 (\u002B3)\n15 (\u002B2)\n10 (\u002B0)\n10 (\u002B0)\n16 (\u002B3)\nDamage Resistances: fire\nDamage Immunities: poison\nCondition Immunities: poisoned\nSenses: darkvision 60 ft., passive Perception 10\nLanguages: Abyssal, Infernal, telepathy 60 ft.\nChallenge: \u0026#8212;\nProficiency Bonus: equals your bonus\nDeath Throes (Demon Only). When the fiend drops to 0 hit points or the spell ends, the fiend explodes, and each creature within 10 feet of it must make a Dexterity saving throw against your spell save DC. A creature takes 2d10 \u002B the spell\u2019s level fire damage on a failed save, or half as much damage on a successful one.\nDevil\u2019s Sight (Devil Only). Magical darkness doesn\u2019t impede the fiend\u2019s darkvision.\nMagic Resistance. The fiend has advantage on saving throws against spells and other magical effects.\nActions\nMultiattack. The fiend makes a number of attacks equal to half this spell\u2019s level (rounded down).\nBite (Demon Only). Melee Weapon Attack: your spell attack modifier to hit, reach 5 ft., one target. Hit: 1d12 \u002B 3 \u002B the spell\u2019s level necrotic damage.\nClaws (Yugoloth Only). Melee Weapon Attack: your spell attack modifier to hit, reach 5 ft., one target. Hit: 1d8 \u002B 3 \u002B the spell\u2019s level slashing damage. Immediately after the attack hits or misses, the fiend can magically teleport up to 30 feet to an unoccupied space it can see.\nHurl Flame (Devil Only). Ranged Spell Attack: your spell attack modifier to hit, range 150 ft., one target. Hit: 2d6 \u002B 3 \u002B the spell\u2019s level fire damage. If the target is a flammable object that isn\u2019t being worn or carried, it also catches fire.","InLists":["Warlock (Optional)","Wizard (Optional)"],"Source":"Tasha\u0027s Cauldron of Everything","CastingTime":"1 action","Components":["V","S","M (humanoid blood inside a ruby vial worth at least 600 gp)"],"Range":"90 feet","Duration":"concentration, up to 1 hour","WikidotLink":"http://dnd5e.wikidot.com//spell:summon-fiend"}