{"Id":275,"Name":"Summon Undead","School":"necromancy","Level":3,"PageContent":"Source: Tasha\u0027s Cauldron of Everything\n3rd-level necromancy\nCasting Time: 1 action\nRange: 90 feet\nComponents: V, S, M (a gilded skull worth at least 300 gp)\nDuration: Concentration, up to 1 hour\nYou call forth an undead spirit. It manifests in an unoccupied space that you can see within range. This corporeal form uses the Undead Spirit stat block. When you cast the spell, choose the creature\u2019s form: Ghostly, Putrid, or Skeletal. The spirit resembles an undead creature with the chosen form, which determines certain traits in its stat block. The creature disappears when it drops to 0 hit points or when the spell ends.\nThe creature is an ally to you and your companions. In combat, the creature shares your initiative count, but it takes its turn immediately after yours. It obeys your verbal commands (no action required by you). If you don\u2019t issue any, it takes the Dodge action and uses its move to avoid danger.\nAt Higher Levels. When you cast this spell using a spell slot of 4th level or higher, use the higher level wherever the spell\u2019s level appears in the stat block.\nSpell Lists. Warlock, Wizard\n\n\nUndead Spirit\n\n\nMedium undead\n\n\nArmor Class: 11 \u002B the level of the spell (natural armor)\n\n\nHit Points: 30 (Ghostly and Putrid only) or 20 (Skeletal only) \u002B 10 for each level of the spell above 3rd\n\n\nSpeed: 30 ft., fly 40 ft. (hover) (Ghostly only)\n\n\nSTR\nDEX\nCON\nINT\nWIS\nCHA\n\n\n12 (\u002B1)\n16 (\u002B3)\n15 (\u002B2)\n4 (\u22123)\n10 (\u002B0)\n9 (\u22121)\n\n\nDamage Immunities: necrotic, poison\n\n\nCondition: Immunities exhaustion, frightened, paralyzed, poisoned\n\n\nSenses: darkvision 60 ft., passive Perception 10\n\n\nLanguages: understands the languages you speak\n\n\nChallenge: \u0026#8212;\n\n\nProficiency Bonus: equals your bonus\n\n\nFestering Aura (Putrid Only). Any creature, other than you, that starts its turn within 5 feet of the spirit must succeed on a Constitution saving throw against your spell save DC or be poisoned until the start of its next turn.\n\n\nIncorporeal Passage (Ghostly Only). The spirit can move through other creatures and objects as if they were difficult terrain. If it ends its turn inside an objects, it is shunted to the nearest unoccupied space and takes 1d10 force damage for every 5 feet traveled.\n\n\nActions\n\n\nMultiattack. The spirit makes a number of attacks equal to half this spell\u2019s level (rounded down).\n\n\nDeathly Touch (Ghostly Only). Melee Weapon Attack: your spell attack modifier to hit, reach 5 ft., one creature. Hit: 1d8 \u002B 3 \u002B the spell\u2019s level necrotic damage, and the creature must succeed on a Wisdom saving throw against your spell save DC or be frightened of the undead until the end of the target\u2019s next turn.\n\n\nGrave Bolt (Skeletal Only). Ranged Spell Attack: your spell attack modifier to hit, range 150 ft., one target. Hit: 2d4 \u002B 3 \u002B the spell\u2019s level necrotic damage.\n\n\nRotting Claw (Putrid Only). Melee Weapon Attack: your spell attack modifier to hit, reach 5 ft., one target. Hit: 1d6 \u002B 3 \u002B the spell\u2019s level slashing damage. If the target is poisoned, it must succeed on a Constitution saving throw against your spell save DC or be paralyzed until the end of its next turn.","InLists":["Warlock","Wizard"],"Source":"Tasha\u0027s Cauldron of Everything","CastingTime":"1 action","Components":["V","S","M (a gilded skull worth at least 300 gp)"],"Range":"90 feet","Duration":"concentration, up to 1 hour"}