{"Id":500,"Name":"Sunburst","School":"evocation","Level":8,"PageContent":"Source: Player\u0027s Handbook\n8th-level evocation\nCasting Time: 1 action\nRange: 150 feet\nComponents: V, S, M (fire and a piece of sunstone)\nDuration: Instantaneous\nBrilliant sunlight flashes in a 60-foot radius centered on a point you choose within range. Each creature in that light must make a Constitution saving throw. On a failed save, a creature takes 12d6 radiant damage and is blinded for 1 minute. On a successful save, it takes half as much damage and isn\u2019t blinded by this spell. Undead and oozes have disadvantage on this saving throw.\nA creature blinded by this spell makes another Constitution saving throw at the end of each of its turns. On a successful save, it is no longer blinded.\nThis spell dispels any darkness in its area that was created by a spell.\nSpell Lists. Cleric, Druid, Sorcerer, Wizard","InLists":["Cleric","Druid","Sorcerer","Wizard"],"Source":"Player\u0027s Handbook","CastingTime":"1 action","Components":["V","S","M (fire and a piece of sunstone)"],"Range":"150 feet","Duration":"instantaneous"}