{"Name":"Tasha\u0027s Hideous Laughter","School":"enchantment","Level":1,"PageContent":"Source: Player\u0027s Handbook\n1st-level enchantment\nCasting Time: 1 action\nRange: 30 feet\nComponents: V, S, M (tiny tarts and a feather that is waved in the air)\nDuration: Concentration, up to 1 minute\nA creature of your choice that you can see within range perceives everything as hilariously funny and falls into fits of laughter if this spell affects it. The target must succeed on a Wisdom saving throw or fall prone, becoming incapacitated and unable to stand up for the duration. A creature with an Intelligence score of 4 or less isn\u2019t affected.\nAt the end of each of its turns, and each time it takes damage, the target can make another Wisdom saving throw. The target has advantage on the saving throw if it\u2019s triggered by damage. On a success, the spell ends.\nSpell Lists. Bard, Wizard","InLists":["Bard","Wizard"],"Source":"Player\u0027s Handbook","CastingTime":"1 action","Components":["V","S","M (tiny tarts and a feather that is waved in the air)"],"Range":"30 feet","Duration":"concentration, up to 1 minute"}