{"Id":40,"Name":"Thaumaturgy","School":"transmutation","Level":0,"PageContent":"Source: Player\u0027s Handbook\nTransmutation cantrip\nCasting Time: 1 action\nRange: 30 feet\nComponents: V\nDuration: Up to 1 minute\nYou manifest a minor wonder, a sign of supernatural power, within range. You create one of the following magical effects within range:\n\nYour voice booms up to three times as loud as normal for 1 minute.\n\n\nYou cause flames to flicker, brighten, dim, or change color for 1 minute.\n\n\nYou cause harmless tremors in the ground for 1 minute.\n\n\nYou create an instantaneous sound that originates from a point of your choice within range, such as a rumble of thunder, the cry of a raven, or ominous whispers.\n\n\nYou instantaneously cause an unlocked door or window to fly open or slam shut.\n\n\nYou alter the appearance of your eyes for 1 minute.\n\nIf you cast this spell multiple times, you can have up to three of its 1-minute effects active at a time, and you can dismiss such an effect as an action.\nSpell Lists. Cleric","InLists":["Cleric"],"Source":"Player\u0027s Handbook","CastingTime":"1 action","Components":["V"],"Range":"30 feet","Duration":"up to 1 minute"}