{"Name":"Thunderwave","School":"evocation","Level":1,"PageContent":"Source: Player\u0027s Handbook\n1st-level evocation\nCasting Time: 1 action\nRange: Self (15-foot cube)\nComponents: V, S\nDuration: Instantaneous\nA wave of thunderous force sweeps out from you. Each creature in a 15-foot cube originating from you must make a Constitution saving throw. On a failed save, a creature takes 2d8 thunder damage and is pushed 10 feet away from you. On a successful save, the creature takes half as much damage and isn\u2019t pushed.\nIn addition, unsecured objects that are completely within the area of effect are automatically pushed 10 feet away from you by the spell\u2019s effect, and the spell emits a thunderous boom audible out to 300 feet.\nAt Higher Levels. When you cast this spell using a spell slot of 2nd level or higher, the damage increases by 1d8 for each slot level above 1st.\nSpell Lists. Bard, Druid, Sorcerer, Wizard","InLists":["Bard","Druid","Sorcerer","Wizard"],"Source":"Player\u0027s Handbook","CastingTime":"1 action","Components":["V","S"],"Range":"self (15-foot cube)","Duration":"instantaneous"}