{"Id":206,"Name":"Warding Bond","School":"abjuration","Level":2,"PageContent":"Source: Player\u0027s Handbook\n2nd-level abjuration\nCasting Time: 1 action\nRange: Touch\nComponents: V, S, M (a pair of platinum rings worth at least 50 gp each, which you and target must wear for the duration)\nDuration: 1 hour\nThis spell wards a willing creature you touch and creates a mystic connection between you and the target until the spell ends.\nWhile the target is within 60 feet of you, it gains a \u002B1 bonus to AC and saving throws, and it has resistance to all damage. Also, each time it takes damage, you take the same amount of damage.\nThe spell ends if you drop to 0 hit points or if you and the target become separated by more than 60 feet. It also ends if the spell is cast again on either of the connected creatures. You can also dismiss the spell as an action.\nSpell Lists. Cleric, Paladin","InLists":["Cleric","Paladin"],"Source":"Player\u0027s Handbook","CastingTime":"1 action","Components":["V","S","M (a pair of platinum rings worth at least 50 gp each","which you and target must wear for the duration)"],"Range":"touch","Duration":"1 hour"}