{"Name": "Witch Bolt", "School": "evocation", "Level": 1, "PageContent": "Source: Player's Handbook\n1st-level evocation\nCasting Time: 1 action\nRange: 30 feet\nComponents: V, S, M (a twig from a tree that has been struck by lightning)\nDuration: Concentration, up to 1 minute\nA beam of crackling, blue energy lances out toward a creature within range, forming a sustained arc of lightning between you and the target. Make a ranged spell attack against that creature. On a hit, the target takes 1d12 lightning damage, and on each of your turns for the duration, you can use your action to deal 1d12 lightning damage to the target automatically. The spell ends if you use your action to do anything else. The spell also ends if the target is ever outside the spell\u2019s range or if it has total cover from you.\nAt Higher Levels. When you cast this spell using a spell slot of 2nd level or higher, the initial damage increases by 1d12 for each slot level above 1st.\nSpell Lists. Sorcerer, Warlock, Wizard", "InLists": ["Sorcerer", "Warlock", "Wizard"], "Source": "Player's Handbook", "CastingTime": "1 action", "Components": ["V", "S", "M (a twig from a tree that has been struck by lightning)"], "Range": "30 feet", "Duration": "concentration, up to 1 minute", "Id": 517}