{"Id":211,"Name":"Wither and Bloom","School":"necromancy","Level":2,"PageContent":"Source: Strixhaven: A Curriculum of Chaos\n2nd-level Necromancy\nCasting Time: 1 action\nRange: 60 feet\nComponents: V, S, M (a withered vine twisted into a loop)\nDuration: Instantaneous\nYou invoke both death and life upon a 10-foot-radius sphere centered on a point within range. Each creature of your choice in that area must make a Constitution saving throw, taking 2d6 necrotic damage on a failed save, or half as much damage on a successful one. Nonmagical vegetation in that area withers.\nIn addition, one creature of your choice in that area can spend and roll one of its unspent Hit Dice and regain a number of hit points equal to the roll plus your spellcasting ability modifier.\nAt Higher Levels. When you cast this spell using a spell slot of 3rd level or higher, the damage increases by 1d6 for each slot above 2nd, and the number of Hit Dice that can be spent and added to the healing roll increases by one for each slot above 2nd.\nSpell Lists. Druid, Sorcerer, Wizard","InLists":["Druid","Sorcerer","Wizard"],"Source":"Strixhaven","CastingTime":"1 action","Components":["V","S","M (a withered vine twisted into a loop)"],"Range":"60 feet","Duration":"instantaneous","WikidotLink":"http://dnd5e.wikidot.com//spell:wither-and-bloom"}