{"Name":"Animal Messenger","School":"enchantment","Level":2,"PageContent":"Source: Player\u0027s Handbook\n2nd-level enchantment (ritual)\nCasting Time: 1 action\nRange: 30 feet\nComponents: V, S, M (a morsel of food)\nDuration: 24 hours\nBy means of this spell, you use an animal to deliver a message. Choose a Tiny beast you can see within range, such as a squirrel, a blue jay, or a bat. You specify a location, which you must have visited, and a recipient who matches a general description, such as \u201Ca man or woman dressed in the uniform of the town guard\u201D or \u201Ca red-haired dwarf wearing a pointed hat.\u201D You also speak a message of up to twenty-five words. The target beast travels for the duration of the spell toward the specified location, covering about 50 miles per 24 hours for a flying messenger, or 25 miles for other animals.\nWhen the messenger arrives, it delivers your message to the creature that you described, replicating the sound of your voice. The messenger speaks only to a creature matching the description you gave. If the messenger doesn\u2019t reach its destination before the spell ends, the message is lost, and the beast makes its way back to where you cast this spell.\nAt Higher Levels. If you cast this spell using a spell slot of 3rd level or higher, the duration of the spell increases by 48 hours for each slot level above 2nd.\nSpell Lists. Bard, Druid, Ranger","InLists":["Bard","Druid","Ranger"],"Source":"Player\u0027s Handbook","CastingTime":"1 action","Components":["V","S","M (a morsel of food)"],"Range":"30 feet","Duration":"24 hours"}