{"Id":403,"Name":"Blade Barrier","School":"evocation","Level":6,"PageContent":"Source: Player\u0027s Handbook\n6th-level evocation\nCasting Time: 1 action\nRange: 90 feet\nComponents: V, S\nDuration: Concentration, up to 10 minutes\nYou create a vertical wall of whirling, razor-sharp blades made of magical energy. The wall appears within range and lasts for the duration. You can make a straight wall up to 100 feet long, 20 feet high, and 5 feet thick, or a ringed wall up to 60 feet in diameter, 20 feet high, and 5 feet thick. The wall provides three-quarters cover to creatures behind it, and its space is difficult terrain.\nWhen a creature enters the wall\u2019s area for the first time on a turn or starts its turn there, the creature must make a Dexterity saving throw. On a failed save, the creature takes 6d10 slashing damage. On a successful save, the creature takes half as much damage.\nSpell Lists. Cleric","InLists":["Cleric"],"Source":"Player\u0027s Handbook","CastingTime":"1 action","Components":["V","S"],"Range":"90 feet","Duration":"concentration, up to 10 minutes"}