{"Name":"Chaos Bolt","School":"evocation","Level":1,"PageContent":"Source: Xanathar\u0027s Guide to Everything\n1st-level evocation\nCasting Time: 1 action\nRange: 120 feet\nComponents: V, S\nDuration: Instantaneous\nYou hurl an undulating, warbling mass of chaotic energy at one creature in range. Make a ranged spell attack against the target. On a hit, the target takes 2d8 \u002B 1d6 damage. Choose one of the d8s. The number rolled on that die determines the attack\u0027s damage type, as shown below.\n\n\nd8\nDamage Type\n\n\n1\nAcid\n\n\n2\nCold\n\n\n3\nFire\n\n\n4\nForce\n\n\n5\nLightning\n\n\n6\nPoison\n\n\n7\nPsychic\n\n\n8\nThunder\n\n\nIf you roll the same number on both d8s, the chaotic energy leaps from the target to a different creature of your choice within 30 feet of it. Make a new attack roll against the new target, and make a new damage roll, which could cause the chaotic energy to leap again.\nA creature can be targeted only once by each casting of this spell.\nAt Higher Levels. When you cast this spell using a spell slot of 2nd level or higher, each target takes 1d6 extra damage of the type rolled for each slot level above 1st.\nSpell Lists. Sorcerer","InLists":["Sorcerer"],"Source":"Xanathar\u0027s Guide to Everything","CastingTime":"1 action","Components":["V","S"],"Range":"120 feet","Duration":"instantaneous"}