{"Name":"Confusion","School":"enchantment","Level":4,"PageContent":"Source: Player\u0027s Handbook\n4th-level enchantment\nCasting Time: 1 action\nRange: 90 feet\nComponents: V, S, M (three nut shells)\nDuration: Concentration, up to 1 minute\nThis spell assaults and twists creatures\u2019 minds, spawning delusions and provoking uncontrolled actions. Each creature in a 10-foot-radius sphere centered on a point you choose within range must succeed on a Wisdom saving throw when you cast this spell or be affected by it.\nAn affected target can\u2019t take reactions and must roll a d10 at the start of each of its turns to determine its behavior for that turn.\n\n\nd10\nBehavior\n\n\n1\nThe creature uses all its movement to move in a random direction. To determine the direction, roll a d8 and assign a direction to each die face. The creature doesn\u2019t take an action this turn.\n\n\n2-6\nThe creature doesn\u2019t move or take actions this turn.\n\n\n7-8\nThe creature uses its action to make a melee attack against a randomly determined creature within its reach. If there is no creature within its reach, the creature does nothing this turn.\n\n\n9-10\nThe creature can act and move normally.\n\n\nAt the end of its turns, an affected target can make a Wisdom saving throw. If it succeeds, this effect ends for that target.\nAt Higher Levels. When you cast this spell using a spell slot of 5th level or higher, the radius of the sphere increases by 5 feet for each slot level above 4th.\nSpell Lists. Bard, Druid, Sorcerer, Wizard","InLists":["Bard","Druid","Sorcerer","Wizard"],"Source":"Player\u0027s Handbook","CastingTime":"1 action","Components":["V","S","M (three nut shells)"],"Range":"90 feet","Duration":"concentration, up to 1 minute"}