{"Name":"Conjure Minor Elementals","School":"conjuration","Level":4,"PageContent":"Source: Player\u0027s Handbook\n4th-level conjuration\nCasting Time: 1 minute\nRange: 90 feet\nComponents: V, S\nDuration: Concentration, up to 1 hour\nYou summon elementals that appear in unoccupied spaces that you can see within range. You choose one the following options for what appears:\n\nOne elemental of challenge rating 2 or lower\n\n\nTwo elementals of challenge rating 1 or lower\n\n\nFour elementals of challenge rating 1/2 or lower\n\n\nEight elementals of challenge rating 1/4 or lower\n\nAn elemental summoned by this spell disappears when it drops to 0 hit points or when the spell ends.\nThe summoned creatures are friendly to you and your companions. Roll initiative for the summoned creatures as a group, which has its own turns. They obey any verbal commands that you issue to them (no action required by you). If you don\u2019t issue any commands to them, they defend themselves from hostile creatures, but otherwise take no actions. The DM has the creatures\u2019 statistics.\nAt Higher Levels. When you cast this spell using certain higher-level spell slots, you choose one of the summoning options above, and more creatures appear: twice as many with a 6th-level slot and three times as many with an 8th-level slot.\nSpell Lists. Druid, Wizard","InLists":["Druid","Wizard"],"Source":"Player\u0027s Handbook","CastingTime":"1 minute","Components":["V","S"],"Range":"90 feet","Duration":"concentration, up to 1 hour"}