{"Id":5,"Name":"Create Bonfire","School":"conjuration","Level":0,"PageContent":"Source: Xanathar\u0027s Guide to Everything\nConjuration cantrip\nCasting Time: 1 action\nRange: 60 feet\nComponents: V, S\nDuration: Concentration, up to 1 minute\nYou create a bonfire on ground that you can see within range. Until the spell ends, the bonfire fills a 5-foot cube. Any creature in the bonfire\u2019s space when you cast the spell must succeed on a Dexterity saving throw or take 1d8 fire damage. A creature must also make the saving throw when it enters the bonfire\u2019s space for the first time on a turn or ends its turn there.\nAt Higher Levels. The spell\u2019s damage increases by 1d8 when you reach 5th level (2d8), 11th level (3d8), and 17th level (4d8).\nSpell Lists. Artificer, Druid, Sorcerer, Warlock, Wizard","InLists":["Artificer","Druid","Sorcerer","Warlock","Wizard"],"Source":"Xanathar\u0027s Guide to Everything","CastingTime":"1 action","Components":["V","S"],"Range":"60 feet","Duration":"concentration, up to 1 minute","WikidotLink":"http://dnd5e.wikidot.com//spell:create-bonfire"}