{"Id":69,"Name":"Detect Magic","School":"divination","Level":1,"PageContent":"Source: Player\u0027s Handbook\n1st-level divination (ritual)\nCasting Time: 1 action\nRange: Self\nComponents: V, S\nDuration: Concentration, up to 10 minutes\nFor the duration, you sense the presence of magic within 30 feet of you. If you sense magic in this way, you can use your action to see a faint aura around any visible creature or object in the area that bears magic, and you learn its school of magic, if any.\nThe spell can penetrate most barriers, but is blocked by 1 foot of stone, 1 inch of common metal, a thin sheet of lead, or 3 feet of wood or dirt.\nSpell Lists. Artificer, Bard, Cleric, Druid, Paladin, Ranger, Sorcerer, Wizard","InLists":["Artificer","Bard","Cleric","Druid","Paladin","Ranger","Sorcerer","Wizard"],"Source":"Player\u0027s Handbook","CastingTime":"1 action","Components":["V","S"],"Range":"self","Duration":"concentration, up to 10 minutes","WikidotLink":"http://dnd5e.wikidot.com//spell:detect-magic"}