{"Id":228,"Name":"Dispel Magic","School":"abjuration","Level":3,"PageContent":"Source: Player\u0027s Handbook\n3rd-level abjuration\nCasting Time: 1 action\nRange: 120 feet\nComponents: V, S\nDuration: Instantaneous\nChoose any creature, object, or magical effect within range. Any spell of 3rd level or lower on the target ends. For each spell of 4th level or higher on the target, make an ability check using your spellcasting ability. The DC equals 10 \u002B the spell\u0027s level. On a successful check, the spell ends.\nAt Higher Levels. When you cast this spell using a spell slot of 4th level or higher, you automatically end the effects of a spell on the target if the spell\u0027s level is equal to or less than the level of the spell slot you used.\nSpell Lists. Artificer, Bard, Cleric, Druid, Paladin, Sorcerer, Warlock, Wizard","InLists":["Artificer","Bard","Cleric","Druid","Paladin","Sorcerer","Warlock","Wizard"],"Source":"Player\u0027s Handbook","CastingTime":"1 action","Components":["V","S"],"Range":"120 feet","Duration":"instantaneous"}