{"Id":299,"Name":"Divination","School":"divination","Level":4,"PageContent":"Source: Player\u0027s Handbook\n4th-level divination (ritual)\nCasting Time: 1 action\nRange: Self\nComponents: V, S, M (incense and a sacrificial offering appropriate to your religion, together worth at least 25 gp, which the spell consumes)\nDuration: Instantaneous\nYour magic and an offering put you in contact with a god or a god\u2019s servants. You ask a single question concerning a specific goal, event, or activity to occur within 7 days. The DM offers a truthful reply. The reply might be a short phrase, a cryptic rhyme, or an omen.\nThe spell doesn\u2019t take into account any possible circumstances that might change the outcome, such as the casting of additional spells or the loss or gain of a companion.\nIf you cast this spell two or more times before finishing your next long rest, there is a cumulative 25 percent chance for each casting after the first that you get a random reading. The DM makes this roll in secret.\nSpell Lists. Cleric, Druid, Wizard","InLists":["Cleric","Druid","Wizard"],"Source":"Player\u0027s Handbook","CastingTime":"1 action","Components":["V","S","M (incense and a sacrificial offering appropriate to your religion","together worth at least 25 gp","which the spell consumes)"],"Range":"self","Duration":"instantaneous"}