{"Id":460,"Name":"Draconic Transformation","School":"transmutation","Level":7,"PageContent":"Source: Fizban\u0027s Treasury of Dragons\n7th-level Transmutation\nCasting Time: 1 Bonus Action\nRange: Self\nComponents: V, S, M (a statuette of a dragon, worth at least 500 gp)\nDuration: Concentration, up to 1 minute\nWith a roar, you draw on the magic of dragons to transform yourself, taking on draconic features. You gain the following benefits until the spell ends:\nBlindsight. You have blindsight with a range of 30 feet. Within that range, you can effectively see anything that isn\u2019t behind total cover, even if you\u2019re blinded or in darkness. Moreover, you can see an invisible creature, unless the creature successfully hides from you.\nBreath Weapon. When you cast this spell, and as a bonus action on subsequent turns for the duration, you can exhale shimmering energy in a 60-foot cone. Each creature in that area must make a Dexterity saving throw, taking 6d8 force damage on a failed save, or half as much damage on a successful one.\nWings. Incorporeal wings sprout from your back, giving you a flying speed of 60 feet.\nSpell Lists. Druid, Sorcerer, Wizard","InLists":["Druid","Sorcerer","Wizard"],"Source":"Fizban\u0027s Treasury of Dragons","CastingTime":"1 bonus action","Components":["V","S","M (a statuette of a dragon","worth at least 500 gp)"],"Range":"self","Duration":"concentration, up to 1 minute","WikidotLink":"http://dnd5e.wikidot.com//spell:draconic-transformation"}