{"Name":"Elemental Bane","School":"transmutation","Level":4,"PageContent":"Source: Xanathar\u0027s Guide to Everything\n4th-level transmutation\nCasting Time: 1 action\nRange: 90 feet\nComponents: V, S\nDuration: Concentration, up to 1 minute\nChoose one creature you can see within range, and choose one of the following damage types: acid, cold, fire, lightning, or thunder. The target must succeed on a Constitution saving throw or be affected by the spell for its duration. The first time each turn the affected target takes damage of the chosen type, the target takes an extra 2d6 damage of that type. Moreover, the target loses any resistance to that damage type until the spell ends.\nAt Higher Levels. When you cast this spell using a spell slot of 5th level or higher, you can target one additional creature for each slot level above 4th. The creatures must be within 30 feet of each other when you target them.\nSpell Lists. Druid, Warlock, Wizard, Artificer","InLists":["Druid","Warlock","Wizard","Artificer"],"Source":"Xanathar\u0027s Guide to Everything","CastingTime":"1 action","Components":["V","S"],"Range":"90 feet","Duration":"concentration, up to 1 minute"}