{"Id":150,"Name":"Enhance Ability","School":"transmutation","Level":2,"PageContent":"Source: Player\u0027s Handbook\n2nd-level transmutation\nCasting Time: 1 action\nRange: Touch\nComponents: V, S, M (fur or a feather from a beast)\nDuration: Concentration, up to 1 hour\nYou touch a creature and bestow upon it a magical enhancement. Choose one of the following effects; the target gains the effect until the spell ends.\nBear\u2019s Endurance. The target has advantage on Constitution checks. It also gains 2d6 temporary hit points, which are lost when the spell ends.\nBull\u2019s Strength. The target has advantage on Strength checks, and their carrying capacity doubles.\nCat\u2019s Grace. The target has advantage on Dexterity checks. It also doesn\u2019t take damage from falling 20 feet or less if it isn\u2019t incapacitated.\nEagle\u2019s Splendor. The target has advantage on Charisma checks.\nFox\u2019s Cunning. The target has advantage on Intelligence checks.\nOwl\u2019s Wisdom. The target has advantage on Wisdom checks.\nAt Higher Levels. When you cast this spell using a spell slot of 3rd level or higher, you can target one additional creature for each slot level above 2nd.\nSpell Lists. Artificer, Bard, Cleric, Druid, Ranger (Optional), Sorcerer, Wizard (Optional)","InLists":["Artificer","Bard","Cleric","Druid","Ranger (Optional)","Sorcerer","Wizard (Optional)"],"Source":"Player\u0027s Handbook","CastingTime":"1 action","Components":["V","S","M (fur or a feather from a beast)"],"Range":"touch","Duration":"concentration, up to 1 hour","WikidotLink":"http://dnd5e.wikidot.com//spell:enhance-ability"}