{"Name":"Feeblemind","School":"enchantment","Level":8,"PageContent":"Source: Player\u0027s Handbook\n8th-level enchantment\nCasting Time: 1 action\nRange: 150 feet\nComponents: V, S, M (a handful of clay, crystal, glass, or mineral spheres)\nDuration: Instantaneous\nYou blast the mind of a creature that you can see within range, attempting to shatter its intellect and personality. The target takes 4d6 psychic damage and must make an Intelligence saving throw.\nOn a failed save, the creature\u2019s Intelligence and Charisma scores become 1. The creature can\u2019t cast spells, activate magic items, understand language, or communicate in any intelligible way. The creature can, however, identify its friends, follow them, and even protect them.\nAt the end of every 30 days, the creature can repeat its saving throw against this spell. If it succeeds on its saving throw, the spell ends. The spell can also be ended by Greater Restoration, Heal, or Wish.\nSpell Lists. Bard, Druid, Warlock, Wizard","InLists":["Bard","Druid","Warlock","Wizard"],"Source":"Player\u0027s Handbook","CastingTime":"1 action","Components":["V","S","M (a handful of clay","crystal","glass","or mineral spheres)"],"Range":"150 feet","Duration":"instantaneous"}