{"Id":365,"Name":"Freedom of the Winds (HB)","School":"abjuration","Level":5,"PageContent":"Source: Tal\u0027Dorei Campaign Setting Reborn\n5th-level abjuration\nCasting Time: 1 action\nRange: Self\nComponents: V, S, M (a scrap of sailcloth)\nDuration: Concentration, up to 10 minutes\nWind wraps around your body, tugging at your hair and clothing as your feet lift off the ground. You gain a flying speed of 60 feet. Additionally, you have advantage on ability checks to avoid being grappled, and on saving throws against being restrained or paralyzed.\nWhen you are targeted by a spell or attack while this spell is in effect, you can use a reaction to teleport up to 60 feet to an unoccupied space you can see. If this movement takes you out of range of the triggering spell or attack, you are unaffected by it. This spell then ends when you reappear.\nSpell Lists. Druid, Ranger, Sorcerer","InLists":["Druid","Ranger","Sorcerer"],"Source":"Tal\u0027Dorei Campaign Setting Reborn","CastingTime":"1 action","Components":["V","S","M (a scrap of sailcloth)"],"Range":"self","Duration":"concentration, up to 10 minutes"}