{"Id":310,"Name":"Gate Seal","School":"abjuration","Level":4,"PageContent":"Source: Planescape - Adventures in the Multiverse\n4th-Level abjuration\nCasting Time: 1 minute\nRange: 60 feet\nComponents: V, S, M (a broken portal key, which the spell consumes)\nDuration: 24 Hours\nYou fortify the fabric of the planes within a 30-foot cube you can see within range. Within that area, portals close and can\u0027t be opened for the duration. Spells and other effects that allow planar travel or open portals such as gate or plane shift, fail if used to enter or leave the area. The cube is stationary.\nAt Higher Levels. When you cast this spell using a spell slot of 6th level or higher, the spell lasts until dispelled.\nSpell Lists. Sorcerer, Warlock, Wizard","InLists":["Sorcerer","Warlock","Wizard"],"Source":"Planescape - Adventures in the Multiverse","CastingTime":"1 minute","Components":["V","S","M (a broken portal key","which the spell consumes)"],"Range":"60 feet","Duration":"24 hours","WikidotLink":"http://dnd5e.wikidot.com//spell:gate-seal"}