{"Id":311,"Name":"Giant Insect","School":"transmutation","Level":4,"PageContent":"Source: Player\u0027s Handbook\n4th-level transmutation\nCasting Time: 1 action\nRange: 30 feet\nComponents: V, S\nDuration: Concentration, up to 10 minutes\nYou transform up to ten centipedes, three spiders, five wasps, or one scorpion within range into giant versions of their natural forms for the duration. A centipede becomes a giant centipede, a spider becaomes a giant spider, a wasp becomes a giant wasp, and a scorpion becomes a giant scorpion.\nEach creature obeys your verbal commands, and in combat, they act on your turn each round. The DM has the statistics for these creatures and resolves their actions and movement.\nA creature remains in its giant size for the duration, until it drops to 0 hit points, or until you use an action to dismiss the effect on it.\nThe DM might allow you to choose different targets. For example, if you transform a bee, its giant version might have the same statistics as a giant wasp.\nSpell Lists. Druid","InLists":["Druid"],"Source":"Player\u0027s Handbook","CastingTime":"1 action","Components":["V","S"],"Range":"30 feet","Duration":"concentration, up to 10 minutes","WikidotLink":"http://dnd5e.wikidot.com//spell:giant-insect"}