{"Id":420,"Name":"Gravity Fissure","School":"evocation","Level":6,"PageContent":"Source: Explorer\u0027s Guide to Wildemount\n6th-level evocation (dunamancy:graviturgy)\nCasting Time: 1 action\nRange: Self (100-foot line)\nComponents: V, S, M (a fistful of iron filings)\nDuration: Instantaneous\nYou manifest a ravine of gravitational energy in a line originating from you that is 100 feet long and 5 feet wide. Each creature in that line must make a Constitution saving throw, taking 8d8 force damage on a failed save, or half as much damage on a successful one.\nEach creature within 10 feet of the line but not in it must succeed on a Constitution saving throw or take 8d8 force damage and be pulled toward the line until the creature is in its area.\nAt Higher Levels. When you cast this spell using a spell slot of 7th level or higher, the damage increases by 1d8 for each slot level above 6th.\nSpell Lists. Wizard","InLists":["Wizard"],"Source":"Explorer\u0027s Guide to Wildemount","CastingTime":"1 action","Components":["V","S","M (a fistful of iron filings)"],"Range":"self (100-foot line)","Duration":"instantaneous"}