{"Id":89,"Name":"Hail of Thorns","School":"conjuration","Level":1,"PageContent":"Source: Player\u0027s Handbook\n1st-level conjuration\nCasting Time: 1 bonus action\nRange: Self\nComponents: V\nDuration: Concentration, up to 1 minute\nThe next time you hit a creature with a ranged weapon attack before the spell ends, this spell creates a rain of thorns that sprouts from your ranged weapon or ammunition. In addition to the normal effect of the attack, the target of the attack and each creature within 5 feet of it must make a Dexterity saving throw. A creature takes 1d10 piercing damage on a failed save, or half as much damage on a successful one.\nAt Higher Levels. If you cast this spell using a spell slot of 2nd level or higher, the damage increases by 1d10 for each slot level above 1st (to a maximum of 6d10).\nSpell Lists. Ranger","InLists":["Ranger"],"Source":"Player\u0027s Handbook","CastingTime":"1 bonus action","Components":["V"],"Range":"self","Duration":"concentration, up to 1 minute"}