{"Id":369,"Name":"Hold Monster","School":"enchantment","Level":5,"PageContent":"Source: Player\u0027s Handbook\n5th-level enchantment\nCasting Time: 1 action\nRange: 90 feet\nComponents: V, S, M (a small, straight piece of iron)\nDuration: Concentration, up to 1 minute\nChoose a creature that you can see within range. The target must succeed on a Wisdom saving throw or be paralyzed for the duration. This spell has no effect on undead. At the end of each of its turns, the target can make another Wisdom saving throw. On a success, the spell ends on the target.\nAt Higher Levels. When you cast this spell using a spell slot of 6th level or higher, you can target one additional creature for each slot level above 5th. The creatures must be within 30 feet of each other when you target them.\nSpell Lists. Bard, Sorcerer, Warlock, Wizard","InLists":["Bard","Sorcerer","Warlock","Wizard"],"Source":"Player\u0027s Handbook","CastingTime":"1 action","Components":["V","S","M (a small","straight piece of iron)"],"Range":"90 feet","Duration":"concentration, up to 1 minute"}