{"Name":"Insect Plague","School":"conjuration","Level":5,"PageContent":"Source: Player\u0027s Handbook\n5th-level conjuration\nCasting Time: 1 action\nRange: 300 feet\nComponents: V, S, M (a few grains of sugar, some kernels of grain, and a smear of fat)\nDuration: Concentration, up to 10 minutes\nSwarming, biting locusts fill a 20-foot-radius sphere centered on a point you choose within range. The sphere spreads around corners. The sphere remains for the duration, and its area is lightly obscured. The sphere\u2019s area is difficult terrain.\nWhen the area appears, each creature in it must make a Constitution saving throw. A creature takes 4d10 piercing damage on a failed save, or half as much damage on a successful one. A creature must also make this saving throw when it enters the spell\u2019s area for the first time on a turn or ends its turn there.\nAt Higher Levels. When you cast this spell using a spell slot of 6th level or higher, the damage increases by 1d10 for each slot level above 5th.\nSpell Lists. Cleric, Druid, Sorcerer","InLists":["Cleric","Druid","Sorcerer"],"Source":"Player\u0027s Handbook","CastingTime":"1 action","Components":["V","S","M (a few grains of sugar","some kernels of grain","and a smear of fat)"],"Range":"300 feet","Duration":"concentration, up to 10 minutes"}