{"Id":169,"Name":"Knock","School":"transmutation","Level":2,"PageContent":"Source: Player\u0027s Handbook\n2nd-level transmutation\nCasting Time: 1 action\nRange: 60 feet\nComponents: V\nDuration: Instantaneous\nChoose an object that you can see within range. The object can be a door, a box, a chest, a set of manacles, a padlock, or another object that contains a mundane or magical means that prevents access.\nA target that is held shut by a mundane lock or that is stuck or barred becomes unlocked, unstuck, or unbarred. If the object has multiple locks, only one of them is unlocked.\nIf you choose a target that is held shut with Arcane Lock, that spell is suppressed for 10 minutes, during which time the target can be opened and shut normally.\nWhen you cast the spell, a loud knock, audible from as far away as 300 feet, emanates from the target object.\nSpell Lists. Bard, Sorcerer, Wizard","InLists":["Bard","Sorcerer","Wizard"],"Source":"Player\u0027s Handbook","CastingTime":"1 action","Components":["V"],"Range":"60 feet","Duration":"instantaneous"}