{"Name":"Phantasmal Killer","School":"illusion","Level":4,"PageContent":"Source: Player\u0027s Handbook\n4th-level illusion\nCasting Time: 1 action\nRange: 120 feet\nComponents: V, S\nDuration: Concentration, up to 1 minute\nYou tap into the nightmares of a creature you can see within range and create an illusory manifestation of its deepest fears, visible only to that creature.\nThe target must make a Wisdom saving throw. On a failed save, the target becomes frightened for the duration. At the end of each of the target\u2019s turns before the spell ends, the target must succeed on a Wisdom saving throw or take 4d10 psychic damage. On a successful save, the spell ends.\nAt Higher Levels. When you cast this spell using a spell slot of 5th level or higher, the damage increases by 1d10 for each slot level above 4th.\nSpell Lists. Bard, Wizard","InLists":["Bard","Wizard"],"Source":"Player\u0027s Handbook","CastingTime":"1 action","Components":["V","S"],"Range":"120 feet","Duration":"concentration, up to 1 minute"}