{"Id":188,"Name":"Pyrotechnics","School":"transmutation","Level":2,"PageContent":"Source: Xanathar\u0027s Guide to Everything\n2nd-level transmutation\nCasting Time: 1 action\nRange: 60 feet\nComponents: V, S\nDuration: Instantaneous\nChoose an area of flame that you can see and that can fit within a 5-foot cube within range. You can extinguish the fire in that area, and you create either fireworks or smoke.\nFireworks. The target explodes with a dazzling display of colors. Each creature within 10 feet of the target must succeed on a Constitution saving throw or become blinded until the end of your next turn.\nSmoke. Thick black smoke spreads out from the target in a 20-foot radius, moving around corners. The area of the smoke is heavily obscured. The smoke persists for 1 minute or until a strong wind disperses it.\nSpell Lists. Bard, Sorcerer, Wizard, Artificer","InLists":["Bard","Sorcerer","Wizard","Artificer"],"Source":"Xanathar\u0027s Guide to Everything","CastingTime":"1 action","Components":["V","S"],"Range":"60 feet","Duration":"instantaneous"}