{"Id":382,"Name":"Raise Dead","School":"necromancy","Level":5,"PageContent":"Source: Player\u0027s Handbook\n5th-level necromancy\nCasting Time: 1 hour\nRange: Touch\nComponents: V, S, M (a diamond worth at least 500 gp, which the spell consumes)\nDuration: Instantaneous\nYou return a dead creature you touch to life, provided that it has been dead no longer than 10 days. If the creature\u2019s soul is both willing and at liberty to rejoin the body, the creature returns to life with 1 hit point.\nThis spell also neutralizes any poison and cures nonmagical diseases that affected the creature at the time it died. This spell doesn\u2019t, however, remove magical diseases, curses, or similar effects; if these aren\u2019t first removed prior to casting the spell, they take effect when the creature returns to life. The spell can\u2019t return an undead creature to life.\nThis spell closes all mortal wounds, but it doesn\u2019t restore missing body parts. If the creature is lacking body parts or organs integral for its survival \u2013 its head, for instance \u2013 the spell automatically fails.\nComing back from the dead is an ordeal. The target takes a -4 penalty to all attack rolls, saving throws, and ability checks. Every time the target finishes a long rest, the penalty is reduced by 1 until it disappears.\nSpell Lists. Bard, Cleric, Paladin","InLists":["Bard","Cleric","Paladin"],"Source":"Player\u0027s Handbook","CastingTime":"1 hour","Components":["V","S","M (a diamond worth at least 500 gp","which the spell consumes)"],"Range":"touch","Duration":"instantaneous"}