{"Id":387,"Name":"Rary\u0027s Telepathic Bond","School":"divination","Level":5,"PageContent":"Source: Player\u0027s Handbook\n5th-level divination (ritual)\nCasting Time: 1 action\nRange: 30 feet\nComponents: V, S, M (pieces of eggshell from two different kinds of creatures)\nDuration: 1 hour\nYou forge a telepathic link among up to eight willing creatures of your choice within range, psychically linking each creature to all the others for the duration. Creatures with Intelligence scores of 2 or less aren\u2019t affected by this spell.\nUntil the spell ends, the targets can communicate telepathically through the bond whether or not they have a common language. The communication is possible over any distance, though it can\u2019t extend to other planes of existence.\nSpell Lists. Bard (Optional), Wizard","InLists":["Bard (Optional)","Wizard"],"Source":"Player\u0027s Handbook","CastingTime":"1 action","Components":["V","S","M (pieces of eggshell from two different kinds of creatures)"],"Range":"30 feet","Duration":"1 hour","WikidotLink":"http://dnd5e.wikidot.com//spell:rarys-telepathic-bond"}