{"Id":200,"Name":"Spike Growth","School":"transmutation","Level":2,"PageContent":"Source: Player\u0027s Handbook\n2nd-level transmutation\nCasting Time: 1 action\nRange: 150 feet\nComponents: V, S, M (seven sharp thorns or seven small twigs, each sharpened to a point)\nDuration: Concentration, up to 10 minutes\nThe ground in a 20-foot radius centered on a point within range twists and sprouts hard spikes and thorns. The area becomes difficult terrain for the duration. When a creature moves into or within the area, it takes 2d4 piercing damage for every 5 feet it travels.\nThe transformation of the ground is camouflaged to look natural. Any creature that can\u2019t see the area at the time the spell is cast must make a Wisdom (Perception) check against your spell save DC to recognize the terrain as hazardous before entering it.\nSpell Lists. Druid, Ranger","InLists":["Druid","Ranger"],"Source":"Player\u0027s Handbook","CastingTime":"1 action","Components":["V","S","M (seven sharp thorns or seven small twigs","each sharpened to a point)"],"Range":"150 feet","Duration":"concentration, up to 10 minutes","WikidotLink":"http://dnd5e.wikidot.com//spell:spike-growth"}