{"Name":"Spirit Shroud","School":"necromancy","Level":3,"PageContent":"Source: Tasha\u0027s Cauldron of Everything\n3rd-level necromancy\nCasting Time: 1 bonus action\nRange: Self\nComponents: V, S\nDuration: Concentration, up to 1 minute\nYou call forth spirits of the dead, which flit around you for the spell\u2019s duration. The spirits are intangible and invulnerable.\nUntil the spell ends, any attack you make deals 1d8 extra damage when you hit a creature within 10 feet of you. This damage is radiant, necrotic, or cold (your choice when you cast the spell). Any creature that takes this damage can\u2019t regain hit points until the start of your next turn.\nIn addition, any creature of your choice that you can see that starts its turn within 10 feet of you has its speed reduced by 10 feet until the start of your next turn.\nAt Higher Levels. When you cast this spell using a spell slot of 4th level or higher, the damage increases by 1d8 for every two slot levels above 3rd.\nSpell Lists. Cleric, Paladin, Warlock, Wizard","InLists":["Cleric","Paladin","Warlock","Wizard"],"Source":"Tasha\u0027s Cauldron of Everything","CastingTime":"1 bonus action","Components":["V","S"],"Range":"self","Duration":"concentration, up to 1 minute"}