{"Name":"Spiritual Weapon","School":"evocation","Level":2,"PageContent":"Source: Player\u0027s Handbook\n2nd-level evocation\nCasting Time: 1 bonus action\nRange: 60 feet\nComponents: V, S\nDuration: 1 minute\nYou create a floating, spectral weapon within range that lasts for the duration or until you cast this spell again.\nWhen you cast the spell, you can make a melee spell attack against a creature within 5 feet of the weapon. On a hit, the target takes force damage equal to 1d8 \u002B your spellcasting ability modifier.\nAs a bonus action on your turn, you can move the weapon up to 20 feet and repeat the attack against a creature within 5 feet of it.\nThe weapon can take whatever form you choose. Clerics of deities who are associated with a particular weapon (as St. Cuthbert is known for his mace and Thor for his hammer) make this spell\u2019s effect resemble that weapon.\nAt Higher Levels. When you cast this spell using a spell slot of 3rd level or higher, the damage increases by 1d8 for every two slot levels above the 2nd.\nSpell Lists. Cleric","InLists":["Cleric"],"Source":"Player\u0027s Handbook","CastingTime":"1 bonus action","Components":["V","S"],"Range":"60 feet","Duration":"1 minute"}