{"Id":202,"Name":"Spray Of Cards","School":"conjuration","Level":2,"PageContent":"Source: The Book of Many Things\n2nd-level conjuration\nCasting Time: 1 action\nRange: Self (15-foot cone)\nComponents: V, S, M (a deck of cards)\nDuration: Instantaneous\nYou spray a 15-foot cone of spectral cards. Each creature in that area must make a Dexterity saving throw. On a failed save, a creature takes 2d10 force damage and has the blinded condition until the end of its next turn. On a successful save, a creature takes half as much damage only.\nAt Higher Levels. When you cast this spell using a spell slot of 3rd level or higher, the damage increases by 1d10 for each slot level above 2nd.\nSpell Lists. Bard, Sorcerer, Warlock, Wizard","InLists":["Bard","Sorcerer","Warlock","Wizard"],"Source":"The Book of Many Things","CastingTime":"1 action","Components":["V","S","M (a deck of cards)"],"Range":"self (15-foot cone)","Duration":"instantaneous","WikidotLink":"http://dnd5e.wikidot.com//spell:spray-of-cards"}