{"Id":332,"Name":"Summon Elemental","School":"conjuration","Level":4,"PageContent":"Source: Tasha\u0027s Cauldron of Everything\n4th-level conjuration\nCasting Time: 1 action\nRange: 90 feet\nComponents: V, S, M (air, a pebble, ash, and water inside a gold-inlaid vial worth at least 400 gp)\nDuration: Concentration, up to 1 hour\nYou call forth an elemental spirit. It manifests in an unoccupied space that you can see within range. This corporeal form uses the Elemental Spirit stat block. When you cast the spell, choose an element: Air, Earth, Fire, or Water. The creature resembles a bipedal form wreathed in the chosen element, which determines certain traits in its stat block. The creature disappears when it drops to 0 hit points or when the spell ends.\nThe creature is an ally to you and your companions. In combat, the creature shares your initiative count, but it takes its turn immediately after yours. It obeys your verbal commands (no action required by you). If you don\u2019t issue any, it takes the Dodge action and uses its move to avoid danger.\nAt Higher Levels. When you cast this spell using a spell slot of 5th level or higher, use the higher level wherever the spell\u2019s level appears in the stat block.\nSpell Lists. Druid, Ranger, Wizard\n\n\nElemental Spirit\n\n\nMedium elemental\n\n\nArmor Class: 11 \u002B the level of the spell (natural armor)\n\n\nHit Points: 50 \u002B 10 for each spell level above 4th\n\n\nSpeed: 40 ft.; burrow 40 ft. (Earth only); fly 40 ft. (hover) (Air only); swim 40 ft. (Water only)\n\n\nSTR\nDEX\nCON\nINT\nWIS\nCHA\n\n\n18 (\u002B4)\n15 (\u002B2)\n17 (\u002B3)\n4 (-3)\n10 (\u002B0)\n16 (\u002B3)\n\n\nDamage Resistances: acid (Water only); lightning and thunder (Air only); piercing and slashing (Earth only)\n\n\nDamage Immunities: poison; fire (Fire only)\n\n\nCondition Immunities: exhaustion, frightened, paralyzed, petrified, petrified, poisoned, unconscious\n\n\nSenses: darkvision 60 ft., passive Perception 10\n\n\nLanguages: Primordial, understands the languages you speak\n\n\nChallenge: \u0026#8212;\n\n\nProficiency Bonus: equals your bonus\n\n\nAmorphous Form (Air, Fire, and Water Only). The elemental can move through a space as narrow as 1 inch wide without squeezing.\n\n\nActions\n\n\nMultiattack. The elemental makes a number of attacks equal to half this spell\u2019s level (rounded down).\n\n\nSlam. Melee Weapon Attack: your spell attack modifier to hit, reach 5 ft., one target. Hit: 1d10 \u002B 4 \u002B the spell\u2019s level bludgeoning damage (Air, Earth, and Water only) or fire damage (Fire only).","InLists":["Druid","Ranger","Wizard"],"Source":"Tasha\u0027s Cauldron of Everything","CastingTime":"1 action","Components":["V","S","M (air","a pebble","ash","and water inside a gold-inlaid vial worth at least 400 gp)"],"Range":"90 feet","Duration":"concentration, up to 1 hour"}