{"Id":393,"Name":"Summon Celestial","School":"conjuration","Level":5,"PageContent":"Source: Tasha\u0027s Cauldron of Everything\n5th-level conjuration\nCasting Time: 1 action\nRange: 90 feet\nComponents: V, S, M (a golden reliquary worth at least 500 gp)\nDuration: Concentration, up to 1 hour\nYou call forth a celestial spirit. It manifests in an angelic form in an unoccupied space that you can see within range. This corporeal form uses the Celestial Spirit stat block. When you cast the spell, choose Avenger or Defender. Your choice determines the creature\u2019s attack in its stat block. The creature disappears when it drops to 0 hit points or when the spell ends.\nThe creature is an ally to you and your companions. In combat, the creature shares your initiative count, but it takes its turn immediately after yours. It obeys your verbal commands (no action required by you). If you don\u2019t issue any, it takes the Dodge action and uses its move to avoid danger.\nAt Higher Levels. When you cast this spell using a spell slot of 6th level or higher, use the higher level whenever the spell\u2019s level appears in the stat block.\nSpell Lists. Cleric (Optional), Paladin (Optional)\nCelestial Spirit\nLarge celestial\nArmor Class: 11 \u002B the level of the spell (natural armor) \u002B 2 (Defender only)\nHit Points: 40 \u002B 10 for each spell level above 5th\nSpeed: 30 ft., fly 40 ft.\nSTR\nDEX\nCON\nINT\nWIS\nCHA\n16 (\u002B3)\n14 (\u002B2)\n16 (\u002B3)\n10 (\u002B0)\n14 (\u002B2)\n16 (\u002B3)\nDamage Resistances: radiant\nCondition Immunities: charmed, frightened\nSenses: darkvision 60 ft., passive Perception 10\nLanguages: Celestial, understands the languages you speak\nChallenge: \u0026#8212;\nProficiency Bonus: equals your bonus\nActions\nMultiattack. The celestial makes a number of attacks equal to half this spell\u2019s level (rounded down).\nRadiant Bow (Avenger Only). Ranged Weapon Attack: your spell attack modifier to hit, reach 150/600 ft., one target. Hit: 2d6 \u002B 2 \u002B the spell\u2019s level radiant damage.\nRadiant Mace (Defender Only). Melee Weapon Attack: your spell attack modifier to hit, reach 5 ft., one target. Hit: 1d10 \u002B 3 \u002B the spell\u2019s level radiant damage, and the celestial can choose itself or another creature it can see within 10 feet of the target. The chosen creature gains 1d10 temporary hit points.\nHealing Touch (1/Day). The celestial touches another creature. The target magically regains hit points equal to 2d8 \u002B the spell\u2019s level.","InLists":["Cleric (Optional)","Paladin (Optional)"],"Source":"Tasha\u0027s Cauldron of Everything","CastingTime":"1 action","Components":["V","S","M (a golden reliquary worth at least 500 gp)"],"Range":"90 feet","Duration":"concentration, up to 1 hour","WikidotLink":"http://dnd5e.wikidot.com//spell:summon-celestial"}