{"Name":"Tasha\u0027s Otherworldly Guise","School":"transmutation","Level":6,"PageContent":"Source: Tasha\u0027s Cauldron of Everything\n6th-level transmutation\nCasting Time: 1 bonus action\nRange: Self\nComponents: V, S, M (an object engraved with a symbol of the Outer Planes, worth at least 500 gp)\nDuration: Concentration, up to 1 minute\nUttering an incantation, you draw on the magic of the Lower Planes or Upper Planes (your choice) to transform yourself. You gain the following benefits until the spell ends:\n\nYou are immune to fire and poison damage (Lower Planes) or radiant and necrotic damage (Upper Planes).\n\n\nYou are immune to the poisoned condition (Lower Planes) or the charmed condition (Upper Planes).\n\n\nSpectral wings appear on your back, giving you a flying speed of 40 feet.\n\n\nYou have a \u002B2 bonus to AC.\n\n\nAll your weapon attacks are magical, and when you make a weapon attack, you can use your spell casting ability modifier instead of Strength or Dexterity for the attack and damage rolls.\n\n\nYou can attack twice, instead of once, when you take the Attack action on your turn. You ignore this benefit if you already have a feature, like Extra Attack, that lets you attack more than once when you take the Attack action on your turn.\n\nSpell Lists. Sorcerer, Warlock, Wizard","InLists":["Sorcerer","Warlock","Wizard"],"Source":"Tasha\u0027s Cauldron of Everything","CastingTime":"1 bonus action","Components":["V","S","M (an object engraved with a symbol of the Outer Planes","worth at least 500 gp)"],"Range":"self","Duration":"concentration, up to 1 minute"}