{"Name":"Tasha\u0027s Mind Whip","School":"enchantment","Level":2,"PageContent":"Source: Tasha\u0027s Cauldron of Everything\n2nd-level enchantment\nCasting Time: 1 action\nRange: 90 feet\nComponents: V\nDuration: 1 round\nYou psychically lash out at one creature you can see within range. The target must make an Intelligence saving throw. On a failed save, the target takes 3d6 psychic damage, and it can\u2019t take a reaction until the end of its next turn. Moreover, on its next turn, it must choose whether it gets a move, an action, or a bonus action; it gets only one of the three. On a successful save, the target takes half as much damage and suffers none of the spell\u2019s other effects.\nAt Higher Levels. When you cast this spell using a spell slot of 3rd level or higher, you can target one additional creature for each slot level above 2nd. The creatures must be within 30 feet of each other when you target them.\nSpell Lists. Sorcerer, Wizard","InLists":["Sorcerer","Wizard"],"Source":"Tasha\u0027s Cauldron of Everything","CastingTime":"1 action","Components":["V"],"Range":"90 feet","Duration":"1 round"}