{"Name":"True Resurrection","School":"necromancy","Level":9,"PageContent":"Source: Player\u0027s Handbook\n9th-level necromancy\nCasting Time: 1 hour\nRange: Touch\nComponents: V, S, M (a sprinkle of holy water and diamonds worth at least 25,000 gp, which the spell consumes)\nDuration: Instantaneous\nYou touch a creature that has been dead for no longer than 200 years and that died for any reason except old age. If the creature\u2019s soul is free and willing, the creature is restored to life with all its hit points.\nThis spell closes all wounds, neutralizes any poison, cures all diseases, and lifts any curses affecting the creature when it died. The spell replaces damaged or missing organs or limbs. If the creature was undead, it is restored to its non-undead form.\nThe spell can even provide a new body if the original no longer exists, in which case you must speak the creature\u2019s name. The creature then appears in an unoccupied space you choose within 10 feet of you.\nSpell Lists. Cleric, Druid","InLists":["Cleric","Druid"],"Source":"Player\u0027s Handbook","CastingTime":"1 hour","Components":["V","S","M (a sprinkle of holy water and diamonds worth at least 25,000 gp","which the spell consumes)"],"Range":"touch","Duration":"instantaneous"}